{"files":[{"name":"314bgm.ogg","ref":[0,0,710626]},{"name":"A_top_1.ogg","ref":[0,710626,1341161]},{"name":"94bgm.ogg","ref":[1,0,551945]},{"name":"A_top_2.ogg","ref":[1,551945,833102]},{"name":"bg_intro.ogg","ref":[1,833102,1079893]},{"name":"C_cymhdfill_12.ogg","ref":[1,1079893,1207853]},{"name":"474bass.ogg","ref":[1,1207853,1334684]},{"name":"94bass.ogg","ref":[1,1334684,1450374]},{"name":"bgm54.ogg","ref":[2,0,111408]},{"name":"474bgm.ogg","ref":[2,111408,209851]},{"name":"C_cym2.ogg","ref":[2,209851,296505]},{"name":"C_guitarsolo_41.ogg","ref":[2,296505,379903]},{"name":"C_metallead_166.ogg","ref":[2,379903,458633]},{"name":"C_cym3.ogg","ref":[2,458633,535987]},{"name":"C_cym1.ogg","ref":[2,535987,607463]},{"name":"32_drop.ogg","ref":[2,607463,674624]},{"name":"42drop.ogg","ref":[2,674624,741116]},{"name":"292bgm.ogg","ref":[2,741116,802266]},{"name":"55_3_ambience.ogg","ref":[2,802266,862355]},{"name":"55.2.4_lastdrop.ogg","ref":[2,862355,921286]},{"name":"B_piano29.ogg","ref":[2,921286,977964]},{"name":"B_piano27.ogg","ref":[2,977964,1034272]},{"name":"A_doremi_1.ogg","ref":[2,1034272,1087901]},{"name":"B_piano21.ogg","ref":[2,1087901,1140398]},{"name":"introLH_48.ogg","ref":[2,1140398,1192353]},{"name":"introlead_65.ogg","ref":[2,1192353,1244238]},{"name":"15gunshot.ogg","ref":[2,1244238,1295877]},{"name":"C_crash_open.ogg","ref":[2,1295877,1347253]},{"name":"introLH_6.ogg","ref":[2,1347253,1397867]},{"name":"A_crsh_mute2.ogg","ref":[2,1397867,1447661]},{"name":"introLH_10.ogg","ref":[3,0,49487]},{"name":"introLH_18.ogg","ref":[3,49487,98609]},{"name":"introLH_49.ogg","ref":[3,98609,147484]},{"name":"B_piano45.ogg","ref":[3,147484,194799]},{"name":"B_piano25.ogg","ref":[3,194799,242005]},{"name":"introLH_13.ogg","ref":[3,242005,289158]},{"name":"A_crsh_mute1.ogg","ref":[3,289158,336094]},{"name":"B_piano61.ogg","ref":[3,336094,382429]},{"name":"introLH_2.ogg","ref":[3,382429,428673]},{"name":"B_piano37.ogg","ref":[3,428673,474614]},{"name":"introLH_33.ogg","ref":[3,474614,519903]},{"name":"introLH_4.ogg","ref":[3,519903,564582]},{"name":"introLH_11.ogg","ref":[3,564582,609241]},{"name":"introLH_8.ogg","ref":[3,609241,653829]},{"name":"introLH_1.ogg","ref":[3,653829,698277]},{"name":"introLH_3.ogg","ref":[3,698277,742277]},{"name":"introLH_53.ogg","ref":[3,742277,786239]},{"name":"introLH_7.ogg","ref":[3,786239,829821]},{"name":"introLH_36.ogg","ref":[3,829821,873215]},{"name":"B_piano16.ogg","ref":[3,873215,915920]},{"name":"B_piano26.ogg","ref":[3,915920,958094]},{"name":"B_piano41.ogg","ref":[3,958094,999671]},{"name":"B_piano9.ogg","ref":[3,999671,1041040]},{"name":"B_piano5.ogg","ref":[3,1041040,1082243]},{"name":"C_guitarsolo_40.ogg","ref":[3,1082243,1123346]},{"name":"introLH_54.ogg","ref":[3,1123346,1164404]},{"name":"B_piano48.ogg","ref":[3,1164404,1205431]},{"name":"B_piano40.ogg","ref":[3,1205431,1246442]},{"name":"B_piano51.ogg","ref":[3,1246442,1287097]},{"name":"A_doremi_2.ogg","ref":[3,1287097,1327749]},{"name":"B_piano28.ogg","ref":[3,1327749,1368280]},{"name":"A_strstab_1.ogg","ref":[3,1368280,1408676]},{"name":"A_doremi_6.ogg","ref":[3,1408676,1449001]},{"name":"B_piano53.ogg","ref":[4,0,39726]},{"name":"B_piano34.ogg","ref":[4,39726,79160]},{"name":"B_piano1.ogg","ref":[4,79160,118521]},{"name":"A_doremi_4.ogg","ref":[4,118521,157760]},{"name":"A_doremi_7.ogg","ref":[4,157760,196999]},{"name":"B_piano3.ogg","ref":[4,196999,236129]},{"name":"B_piano20.ogg","ref":[4,236129,274625]},{"name":"A_lead1_56.ogg","ref":[4,274625,313051]},{"name":"B_piano43.ogg","ref":[4,313051,351464]},{"name":"A_crsh_L_.3.ogg","ref":[4,351464,389813]},{"name":"A_LaidLEAD_112.ogg","ref":[4,389813,427888]},{"name":"B_piano52.ogg","ref":[4,427888,465941]},{"name":"B_piano7.ogg","ref":[4,465941,503639]},{"name":"B_piano17.ogg","ref":[4,503639,541249]},{"name":"A_strstab_2.ogg","ref":[4,541249,578303]},{"name":"B_piano24.ogg","ref":[4,578303,615138]},{"name":"B_piano12.ogg","ref":[4,615138,651967]},{"name":"A_acsnare_26.ogg","ref":[4,651967,688672]},{"name":"introLH_5.ogg","ref":[4,688672,725297]},{"name":"B_piano54.ogg","ref":[4,725297,761204]},{"name":"introLH_9.ogg","ref":[4,761204,796698]},{"name":"40_tapestop.ogg","ref":[4,796698,831741]},{"name":"93_reverse.ogg","ref":[4,831741,866740]},{"name":"C_hats_5open.ogg","ref":[4,866740,901469]},{"name":"B_piano4.ogg","ref":[4,901469,936035]},{"name":"B_piano33.ogg","ref":[4,936035,970565]},{"name":"introLH_17.ogg","ref":[4,970565,1005002]},{"name":"A_mainpiano_15.ogg","ref":[4,1005002,1039427]},{"name":"14water.ogg","ref":[4,1039427,1073844]},{"name":"introLH_29.ogg","ref":[4,1073844,1108193]},{"name":"A_mainpiano_19.ogg","ref":[4,1108193,1142517]},{"name":"A_mainpiano_10.ogg","ref":[4,1142517,1176813]},{"name":"A_mainpiano_8.ogg","ref":[4,1176813,1211034]},{"name":"C_snare_106.ogg","ref":[4,1211034,1245206]},{"name":"A_mainpiano_23.ogg","ref":[4,1245206,1279338]},{"name":"introLH_31.ogg","ref":[4,1279338,1313400]},{"name":"A_mainpiano_5.ogg","ref":[4,1313400,1347378]},{"name":"introLH_16.ogg","ref":[4,1347378,1381338]},{"name":"A_mainpiano_13.ogg","ref":[4,1381338,1415242]},{"name":"A_mainpiano_25.ogg","ref":[4,1415242,1449104]},{"name":"introLH_24.ogg","ref":[5,0,33856]},{"name":"A_mainpiano_24.ogg","ref":[5,33856,67637]},{"name":"A_mainpiano_26.ogg","ref":[5,67637,101392]},{"name":"A_uppiano_2.ogg","ref":[5,101392,135142]},{"name":"introLH_27.ogg","ref":[5,135142,168851]},{"name":"A_mainpiano_16.ogg","ref":[5,168851,202558]},{"name":"B_piano32.ogg","ref":[5,202558,236248]},{"name":"B_piano46.ogg","ref":[5,236248,269833]},{"name":"A_uppiano_25.ogg","ref":[5,269833,303399]},{"name":"introLH_28.ogg","ref":[5,303399,336952]},{"name":"A_uppiano_7.ogg","ref":[5,336952,370472]},{"name":"C_snare_127.ogg","ref":[5,370472,403976]},{"name":"A_uppiano_12.ogg","ref":[5,403976,437368]},{"name":"B_piano6.ogg","ref":[5,437368,470743]},{"name":"introLH_14.ogg","ref":[5,470743,504105]},{"name":"A_uppiano_35.ogg","ref":[5,504105,537432]},{"name":"B_piano19.ogg","ref":[5,537432,570711]},{"name":"A_uppiano_13.ogg","ref":[5,570711,603984]},{"name":"introLH_26.ogg","ref":[5,603984,637250]},{"name":"A_uppiano_30.ogg","ref":[5,637250,670512]},{"name":"introLH_23.ogg","ref":[5,670512,703767]},{"name":"A_uppiano_28.ogg","ref":[5,703767,737019]},{"name":"B_piano50.ogg","ref":[5,737019,770173]},{"name":"introLH_19.ogg","ref":[5,770173,803291]},{"name":"introLH_21.ogg","ref":[5,803291,836399]},{"name":"A_uppiano_33.ogg","ref":[5,836399,869496]},{"name":"introLH_25.ogg","ref":[5,869496,902481]},{"name":"A_kick_3.ogg","ref":[5,902481,935439]},{"name":"B_piano2.ogg","ref":[5,935439,968382]},{"name":"B_piano44.ogg","ref":[5,968382,1001324]},{"name":"A_uppiano_5.ogg","ref":[5,1001324,1034225]},{"name":"B_piano14.ogg","ref":[5,1034225,1067048]},{"name":"A_uppiano_14.ogg","ref":[5,1067048,1099868]},{"name":"A_uppiano_4.ogg","ref":[5,1099868,1132687]},{"name":"A_uppiano_37.ogg","ref":[5,1132687,1165489]},{"name":"A_uppiano_15.ogg","ref":[5,1165489,1198221]},{"name":"B_piano55.ogg","ref":[5,1198221,1230944]},{"name":"introLH_22.ogg","ref":[5,1230944,1263652]},{"name":"introLH_15.ogg","ref":[5,1263652,1296182]},{"name":"A_uppiano_8.ogg","ref":[5,1296182,1328631]},{"name":"introLH_12.ogg","ref":[5,1328631,1360987]},{"name":"B_piano23.ogg","ref":[5,1360987,1393261]},{"name":"B_piano42.ogg","ref":[5,1393261,1425533]},{"name":"B_piano8.ogg","ref":[5,1425533,1457778]},{"name":"B_piano22.ogg","ref":[6,0,32130]},{"name":"B_piano10.ogg","ref":[6,32130,64249]},{"name":"introLH_51.ogg","ref":[6,64249,96337]},{"name":"C_snare_rim_127.ogg","ref":[6,96337,128408]},{"name":"A_mainpiano_14.ogg","ref":[6,128408,160118]},{"name":"A_mainpiano_1.ogg","ref":[6,160118,191781]},{"name":"introLH_20.ogg","ref":[6,191781,223347]},{"name":"B_piano49.ogg","ref":[6,223347,254908]},{"name":"B_piano15.ogg","ref":[6,254908,286456]},{"name":"A_uppiano_26.ogg","ref":[6,286456,317956]},{"name":"A_mainpiano_12.ogg","ref":[6,317956,349453]},{"name":"A_mainpiano_18.ogg","ref":[6,349453,380936]},{"name":"A_mainpiano_3.ogg","ref":[6,380936,412402]},{"name":"A_mainpiano_6.ogg","ref":[6,412402,443848]},{"name":"A_uppiano_9.ogg","ref":[6,443848,475292]},{"name":"B_piano30.ogg","ref":[6,475292,506704]},{"name":"introLH_52.ogg","ref":[6,506704,538059]},{"name":"A_mainpiano_2.ogg","ref":[6,538059,569410]},{"name":"A_crsh_L_.6.ogg","ref":[6,569410,600735]},{"name":"A_uppiano_31.ogg","ref":[6,600735,632038]},{"name":"25.2_reversecym.ogg","ref":[6,632038,663329]},{"name":"introLH_30.ogg","ref":[6,663329,694620]},{"name":"B_piano36.ogg","ref":[6,694620,725891]},{"name":"A_mainpiano_17.ogg","ref":[6,725891,757156]},{"name":"introLH_50.ogg","ref":[6,757156,788354]},{"name":"B_piano18.ogg","ref":[6,788354,819544]},{"name":"A_mainpiano_9.ogg","ref":[6,819544,850719]},{"name":"A_mainpiano_4.ogg","ref":[6,850719,881823]},{"name":"A_mainpiano_21.ogg","ref":[6,881823,912891]},{"name":"A_uppiano_27.ogg","ref":[6,912891,943915]},{"name":"A_mainpiano_7.ogg","ref":[6,943915,974892]},{"name":"A_14basswav_105.ogg","ref":[6,974892,1005806]},{"name":"A_mainpiano_22.ogg","ref":[6,1005806,1036689]},{"name":"A_uppiano_34.ogg","ref":[6,1036689,1067552]},{"name":"A_uppiano_11.ogg","ref":[6,1067552,1098357]},{"name":"A_uppiano_23_.ogg","ref":[6,1098357,1129155]},{"name":"introLH_34.ogg","ref":[6,1129155,1159951]},{"name":"A_mainpiano_20.ogg","ref":[6,1159951,1190743]},{"name":"A_uppiano_1.ogg","ref":[6,1190743,1221529]},{"name":"A_mainpiano_11.ogg","ref":[6,1221529,1252303]},{"name":"A_uppiano_24.ogg","ref":[6,1252303,1282993]},{"name":"A_uppiano_6.ogg","ref":[6,1282993,1313577]},{"name":"A_uppiano_29.ogg","ref":[6,1313577,1344123]},{"name":"B_piano11.ogg","ref":[6,1344123,1374642]},{"name":"21.3_reversecym.ogg","ref":[6,1374642,1405112]},{"name":"A_uppiano_3.ogg","ref":[6,1405112,1435566]},{"name":"A_uppiano_32.ogg","ref":[6,1435566,1465928]},{"name":"C_crash_dld_1.ogg","ref":[7,0,30331]},{"name":"B_piano39.ogg","ref":[7,30331,60612]},{"name":"A_uppiano_36.ogg","ref":[7,60612,90722]},{"name":"A_uppiano_10.ogg","ref":[7,90722,120671]},{"name":"A_uppiano_16.ogg","ref":[7,120671,150589]},{"name":"B_piano47.ogg","ref":[7,150589,180467]},{"name":"A_uppiano_38.ogg","ref":[7,180467,210318]},{"name":"C_crash_dld_4.ogg","ref":[7,210318,240132]},{"name":"B_piano38.ogg","ref":[7,240132,269895]},{"name":"A_uppiano_17.ogg","ref":[7,269895,299641]},{"name":"B_piano31.ogg","ref":[7,299641,329338]},{"name":"B_piano35.ogg","ref":[7,329338,359029]},{"name":"A_uppiano_39.ogg","ref":[7,359029,388656]},{"name":"A_doremi_5.ogg","ref":[7,388656,417703]},{"name":"A_doremi_8.ogg","ref":[7,417703,446750]},{"name":"A_doremi_10.ogg","ref":[7,446750,475348]},{"name":"introLH_35.ogg","ref":[7,475348,503914]},{"name":"A_bubble_2.ogg","ref":[7,503914,532380]},{"name":"C_guitarsolo_1.ogg","ref":[7,532380,560774]},{"name":"A_doremi_9.ogg","ref":[7,560774,588696]},{"name":"A_bubble_1.ogg","ref":[7,588696,616501]},{"name":"A_hihat_7.ogg","ref":[7,616501,644216]},{"name":"A_doremi_3.ogg","ref":[7,644216,671525]},{"name":"A_hihat_18.ogg","ref":[7,671525,698241]},{"name":"introLH_32.ogg","ref":[7,698241,724840]},{"name":"C_hats_9.ogg","ref":[7,724840,749463]},{"name":"A_laidbass_49.ogg","ref":[7,749463,773000]},{"name":"A_pianosqstab_12.ogg","ref":[7,773000,796525]},{"name":"A_crsh_R_.7.ogg","ref":[7,796525,819160]},{"name":"A_crsh_R_.1.ogg","ref":[7,819160,841764]},{"name":"A_LaidLEAD_51.ogg","ref":[7,841764,864038]},{"name":"C_metallead_98.ogg","ref":[7,864038,886243]},{"name":"A_crsh_R_.8.ogg","ref":[7,886243,908430]},{"name":"A_acsnare_14.ogg","ref":[7,908430,930075]},{"name":"A_laidbass_101.ogg","ref":[7,930075,951632]},{"name":"A_crsh_spl_.3.ogg","ref":[7,951632,972975]},{"name":"delayedstackcym.ogg","ref":[7,972975,994251]},{"name":"C_guitarsolo_4.ogg","ref":[7,994251,1015394]},{"name":"A_crsh_R_.2.ogg","ref":[7,1015394,1036515]},{"name":"A_seclead_58.ogg","ref":[7,1036515,1057522]},{"name":"A_acsnare_3.ogg","ref":[7,1057522,1078481]},{"name":"A_lead1_155.ogg","ref":[7,1078481,1099326]},{"name":"A_minitom_2.ogg","ref":[7,1099326,1120096]},{"name":"A_crsh_L_.5.ogg","ref":[7,1120096,1140846]},{"name":"A_crsh_L_.1.ogg","ref":[7,1140846,1161591]},{"name":"C_guitarsolo_33.ogg","ref":[7,1161591,1182139]},{"name":"A_crsh_L_.2.ogg","ref":[7,1182139,1202378]},{"name":"C_guitarsolo_16.ogg","ref":[7,1202378,1222606]},{"name":"C_hats_3.ogg","ref":[7,1222606,1242509]},{"name":"C_hats_12.ogg","ref":[7,1242509,1262281]},{"name":"C_metallead_99.ogg","ref":[7,1262281,1281906]},{"name":"A_acsnare_5.ogg","ref":[7,1281906,1301516]},{"name":"A_crsh_R_.5.ogg","ref":[7,1301516,1321078]},{"name":"A_crsh_R_.4.ogg","ref":[7,1321078,1340610]},{"name":"C_guitarsolo_32.ogg","ref":[7,1340610,1360110]},{"name":"C_hats_4pedal.ogg","ref":[7,1360110,1379258]},{"name":"A_wapad_6.ogg","ref":[7,1379258,1398377]},{"name":"A_wapad_3.ogg","ref":[7,1398377,1417272]},{"name":"41.3reverse.ogg","ref":[7,1417272,1436153]},{"name":"A_lead1_54.ogg","ref":[7,1436153,1454995]},{"name":"C_crash_double.ogg","ref":[7,1454995,1473764]},{"name":"A_glass.ogg","ref":[8,0,18657]},{"name":"introlead_22.ogg","ref":[8,18657,37181]},{"name":"A_LaidLEAD_106.ogg","ref":[8,37181,55669]},{"name":"introlead_64.ogg","ref":[8,55669,74142]},{"name":"A_Keys1_11.ogg","ref":[8,74142,92267]},{"name":"introlead_16.ogg","ref":[8,92267,110350]},{"name":"introlead_1.ogg","ref":[8,110350,128422]},{"name":"1233foley.ogg","ref":[8,128422,146470]},{"name":"C_hats_6.ogg","ref":[8,146470,164286]},{"name":"introlead_7.ogg","ref":[8,164286,181984]},{"name":"C_snare_rim_117.ogg","ref":[8,181984,199566]},{"name":"B_stupiano_7.ogg","ref":[8,199566,217011]},{"name":"C_snare_side_111.ogg","ref":[8,217011,234446]},{"name":"C_snare_90.ogg","ref":[8,234446,251871]},{"name":"C_snare_rim_90.ogg","ref":[8,251871,269272]},{"name":"A_uppiano_41.ogg","ref":[8,269272,286511]},{"name":"C_snare_rim_107.ogg","ref":[8,286511,303747]},{"name":"C_snare_80.ogg","ref":[8,303747,320917]},{"name":"A_uppiano_19.ogg","ref":[8,320917,337816]},{"name":"A_uppiano_40.ogg","ref":[8,337816,354695]},{"name":"49.4reverbsnare.ogg","ref":[8,354695,371517]},{"name":"C_lotom_4.ogg","ref":[8,371517,388109]},{"name":"C_lotom_2.ogg","ref":[8,388109,404551]},{"name":"C_lotom_1.ogg","ref":[8,404551,420990]},{"name":"C_midtom_4.ogg","ref":[8,420990,437409]},{"name":"C_hitom_4.ogg","ref":[8,437409,453771]},{"name":"C_midtom_3.ogg","ref":[8,453771,470126]},{"name":"C_midtom_1.ogg","ref":[8,470126,486340]},{"name":"A_14basswav_51.ogg","ref":[8,486340,502521]},{"name":"17.3.3_laserrrr.ogg","ref":[8,502521,518633]},{"name":"A_uppiano_43.ogg","ref":[8,518633,534735]},{"name":"C_snare_side_127.ogg","ref":[8,534735,550788]},{"name":"C_hitom_2.ogg","ref":[8,550788,566803]},{"name":"A_uppiano_18.ogg","ref":[8,566803,582467]},{"name":"C_lotom_3.ogg","ref":[8,582467,598129]},{"name":"introLH_45.ogg","ref":[8,598129,613786]},{"name":"sidesnare_12.ogg","ref":[8,613786,629434]},{"name":"A_uppiano_44.ogg","ref":[8,629434,644993]},{"name":"A_uppiano_22.ogg","ref":[8,644993,660490]},{"name":"introLH_47.ogg","ref":[8,660490,675940]},{"name":"introLH_38.ogg","ref":[8,675940,691382]},{"name":"introLH_40.ogg","ref":[8,691382,706786]},{"name":"C_midtom_2.ogg","ref":[8,706786,722178]},{"name":"introLH_44.ogg","ref":[8,722178,737526]},{"name":"C_hitom_3.ogg","ref":[8,737526,752847]},{"name":"C_crash_6_4.ogg","ref":[8,752847,768148]},{"name":"A_uppiano_21.ogg","ref":[8,768148,783429]},{"name":"A_shaker_scr.ogg","ref":[8,783429,798667]},{"name":"introLH_37.ogg","ref":[8,798667,813869]},{"name":"A_uppiano_42.ogg","ref":[8,813869,829049]},{"name":"A_uppiano_20.ogg","ref":[8,829049,844225]},{"name":"introLH_46.ogg","ref":[8,844225,859396]},{"name":"A_lead1_62.ogg","ref":[8,859396,874534]},{"name":"introLH_41.ogg","ref":[8,874534,889663]},{"name":"A_kick_4.ogg","ref":[8,889663,904781]},{"name":"A_lead1_63.ogg","ref":[8,904781,919885]},{"name":"introLH_39.ogg","ref":[8,919885,934974]},{"name":"C_hitom_1.ogg","ref":[8,934974,950014]},{"name":"introLH_42.ogg","ref":[8,950014,965008]},{"name":"introLH_43.ogg","ref":[8,965008,979966]},{"name":"A_kick_5.ogg","ref":[8,979966,994854]},{"name":"A_snare_5.ogg","ref":[8,994854,1009682]},{"name":"A_lead1_6.ogg","ref":[8,1009682,1024483]},{"name":"A_snare_4.ogg","ref":[8,1024483,1039272]},{"name":"A_lead1_7.ogg","ref":[8,1039272,1054031]},{"name":"A_snare_3.ogg","ref":[8,1054031,1068755]},{"name":"A_snare_2.ogg","ref":[8,1068755,1083433]},{"name":"A_pianosqstab_9.ogg","ref":[8,1083433,1097814]},{"name":"A_laidbass_27.ogg","ref":[8,1097814,1112019]},{"name":"A_pianosqstab_8.ogg","ref":[8,1112019,1126176]},{"name":"A_pianosqstab_7.ogg","ref":[8,1126176,1140332]},{"name":"A_laidbass_79.ogg","ref":[8,1140332,1154371]},{"name":"A_lead1_5.ogg","ref":[8,1154371,1168377]},{"name":"A_laidbass_104.ogg","ref":[8,1168377,1182238]},{"name":"A_lead1_45.ogg","ref":[8,1182238,1196083]},{"name":"A_lead1_60.ogg","ref":[8,1196083,1209910]},{"name":"A_pianosqstab_10.ogg","ref":[8,1209910,1223707]},{"name":"A_lead1_61.ogg","ref":[8,1223707,1237501]},{"name":"A_laidbass_26.ogg","ref":[8,1237501,1251267]},{"name":"A_laidbass_103.ogg","ref":[8,1251267,1264975]},{"name":"A_LaidLEAD_79.ogg","ref":[8,1264975,1278628]},{"name":"A_lead1_4.ogg","ref":[8,1278628,1292233]},{"name":"A_laidbass_23.ogg","ref":[8,1292233,1305814]},{"name":"A_laidbass_51.ogg","ref":[8,1305814,1319385]},{"name":"A_laidbass_52.ogg","ref":[8,1319385,1332938]},{"name":"A_lead1_110.ogg","ref":[8,1332938,1346491]},{"name":"A_pianosqstab_11.ogg","ref":[8,1346491,1360040]},{"name":"A_laidbass_75.ogg","ref":[8,1360040,1373496]},{"name":"A_pianosqstab_5.ogg","ref":[8,1373496,1386890]},{"name":"A_lead1_2.ogg","ref":[8,1386890,1400251]},{"name":"A_elecbass_33.ogg","ref":[8,1400251,1413607]},{"name":"A_laidbass_78.ogg","ref":[8,1413607,1426959]},{"name":"A_LaidLEAD_90.ogg","ref":[8,1426959,1440246]},{"name":"A_LaidLEAD_91.ogg","ref":[8,1440246,1453507]},{"name":"A_laidbass_25.ogg","ref":[8,1453507,1466761]},{"name":"A_laidbass_90.ogg","ref":[9,0,13238]},{"name":"A_pianosqstab_4.ogg","ref":[9,13238,26471]},{"name":"A_laidbass_96.ogg","ref":[9,26471,39690]},{"name":"A_LaidLEAD_26.ogg","ref":[9,39690,52907]},{"name":"A_laidbass_77.ogg","ref":[9,52907,66120]},{"name":"A_lead1_58.ogg","ref":[9,66120,79307]},{"name":"A_pianosqstab_1.ogg","ref":[9,79307,92481]},{"name":"A_pianosqstab_6.ogg","ref":[9,92481,105631]},{"name":"A_laidbass_63.ogg","ref":[9,105631,118756]},{"name":"C_guitarsolo_38.ogg","ref":[9,118756,131830]},{"name":"C_guitarsolo_29.ogg","ref":[9,131830,144899]},{"name":"A_laidbass_11.ogg","ref":[9,144899,157950]},{"name":"A_LaidLEAD_80.ogg","ref":[9,157950,171001]},{"name":"A_laidbass_14.ogg","ref":[9,171001,184051]},{"name":"A_elecbass_49.ogg","ref":[9,184051,197098]},{"name":"A_LaidLEAD_81.ogg","ref":[9,197098,210138]},{"name":"A_LaidLEAD_29.ogg","ref":[9,210138,223170]},{"name":"A_laidbass_66.ogg","ref":[9,223170,236194]},{"name":"C_guitarsolo_27.ogg","ref":[9,236194,249202]},{"name":"A_laidbass_36.ogg","ref":[9,249202,262200]},{"name":"A_crsh_spl_.1.ogg","ref":[9,262200,275162]},{"name":"A_laidbass_43.ogg","ref":[9,275162,288118]},{"name":"A_laidbass_38.ogg","ref":[9,288118,301055]},{"name":"A_pianosqstab_2.ogg","ref":[9,301055,313954]},{"name":"A_laidbass_35.ogg","ref":[9,313954,326842]},{"name":"A_laidbass_95.ogg","ref":[9,326842,339693]},{"name":"A_lead1_95.ogg","ref":[9,339693,352539]},{"name":"A_laidbass_97.ogg","ref":[9,352539,365369]},{"name":"A_LaidLEAD_72.ogg","ref":[9,365369,378193]},{"name":"A_laidbass_22.ogg","ref":[9,378193,391013]},{"name":"A_laidbass_8.ogg","ref":[9,391013,403832]},{"name":"A_elecbass_34.ogg","ref":[9,403832,416643]},{"name":"A_laidbass_99.ogg","ref":[9,416643,429446]},{"name":"A_laidbass_28.ogg","ref":[9,429446,442247]},{"name":"C_metallead_67.ogg","ref":[9,442247,455045]},{"name":"A_laidbass_87.ogg","ref":[9,455045,467835]},{"name":"A_LaidLEAD_76.ogg","ref":[9,467835,480624]},{"name":"C_metallead_133.ogg","ref":[9,480624,493406]},{"name":"A_LaidLEAD_92.ogg","ref":[9,493406,506184]},{"name":"A_LaidLEAD_82.ogg","ref":[9,506184,518933]},{"name":"A_laidbass_30.ogg","ref":[9,518933,531680]},{"name":"A_lead1_51.ogg","ref":[9,531680,544420]},{"name":"A_laidbass_44.ogg","ref":[9,544420,557146]},{"name":"A_laidbass_88.ogg","ref":[9,557146,569869]},{"name":"A_laidbass_93.ogg","ref":[9,569869,582588]},{"name":"A_laidbass_17.ogg","ref":[9,582588,595303]},{"name":"A_laidbass_60.ogg","ref":[9,595303,608006]},{"name":"A_laidbass_69.ogg","ref":[9,608006,620704]},{"name":"C_kick_2.ogg","ref":[9,620704,633389]},{"name":"A_laidbass_31.ogg","ref":[9,633389,646059]},{"name":"A_LaidLEAD_36.ogg","ref":[9,646059,658723]},{"name":"A_laidbass_74.ogg","ref":[9,658723,671365]},{"name":"C_hats_2.ogg","ref":[9,671365,683986]},{"name":"A_laidbass_100.ogg","ref":[9,683986,696591]},{"name":"A_laidbass_16.ogg","ref":[9,696591,709191]},{"name":"A_laidbass_29.ogg","ref":[9,709191,721783]},{"name":"A_laidbass_33.ogg","ref":[9,721783,734366]},{"name":"A_LaidLEAD_111.ogg","ref":[9,734366,746936]},{"name":"A_elecbass_19.ogg","ref":[9,746936,759502]},{"name":"A_laidbass_55.ogg","ref":[9,759502,772032]},{"name":"A_laidbass_1.ogg","ref":[9,772032,784559]},{"name":"A_laidbass_98.ogg","ref":[9,784559,797086]},{"name":"A_acsnare_8.ogg","ref":[9,797086,809607]},{"name":"A_LaidLEAD_5.ogg","ref":[9,809607,822124]},{"name":"A_laidbass_15.ogg","ref":[9,822124,834637]},{"name":"A_laidbass_20.ogg","ref":[9,834637,847149]},{"name":"A_LaidLEAD_57.ogg","ref":[9,847149,859654]},{"name":"A_laidbass_6.ogg","ref":[9,859654,872158]},{"name":"A_laidbass_83.ogg","ref":[9,872158,884659]},{"name":"A_hihat_1.ogg","ref":[9,884659,897148]},{"name":"stab_3.ogg","ref":[9,897148,909636]},{"name":"A_hihat_phr_5.ogg","ref":[9,909636,922119]},{"name":"A_laidbass_2.ogg","ref":[9,922119,934601]},{"name":"A_LaidLEAD_73.ogg","ref":[9,934601,947081]},{"name":"A_laidbass_19.ogg","ref":[9,947081,959559]},{"name":"A_swinghat_4.ogg","ref":[9,959559,972036]},{"name":"C_metallead_80.ogg","ref":[9,972036,984512]},{"name":"A_laidbass_48.ogg","ref":[9,984512,996984]},{"name":"A_lead1_59.ogg","ref":[9,996984,1009453]},{"name":"A_laidbass_21.ogg","ref":[9,1009453,1021921]},{"name":"C_metallead_62.ogg","ref":[9,1021921,1034380]},{"name":"A_laidbass_39.ogg","ref":[9,1034380,1046838]},{"name":"A_laidbass_85.ogg","ref":[9,1046838,1059295]},{"name":"A_seclead_46.ogg","ref":[9,1059295,1071749]},{"name":"A_elecbass_21.ogg","ref":[9,1071749,1084201]},{"name":"A_laidbass_80.ogg","ref":[9,1084201,1096638]},{"name":"A_laidbass_81.ogg","ref":[9,1096638,1109070]},{"name":"A_laidbass_9.ogg","ref":[9,1109070,1121495]},{"name":"A_LaidLEAD_42.ogg","ref":[9,1121495,1133918]},{"name":"A_laidbass_32.ogg","ref":[9,1133918,1146335]},{"name":"A_laidbass_58.ogg","ref":[9,1146335,1158747]},{"name":"C_metallead_162.ogg","ref":[9,1158747,1171158]},{"name":"A_hihat_2.ogg","ref":[9,1171158,1183568]},{"name":"A_laidbass_12.ogg","ref":[9,1183568,1195976]},{"name":"A_laidbass_4.ogg","ref":[9,1195976,1208383]},{"name":"A_laidbass_56.ogg","ref":[9,1208383,1220790]},{"name":"stab_1.ogg","ref":[9,1220790,1233196]},{"name":"A_Keys1_2.ogg","ref":[9,1233196,1245591]},{"name":"A_laidbass_73.ogg","ref":[9,1245591,1257970]},{"name":"A_hihat_12.ogg","ref":[9,1257970,1270347]},{"name":"A_laidbass_37.ogg","ref":[9,1270347,1282721]},{"name":"A_lead1_39.ogg","ref":[9,1282721,1295088]},{"name":"A_acsnare_22.ogg","ref":[9,1295088,1307448]},{"name":"A_laidbass_61.ogg","ref":[9,1307448,1319808]},{"name":"A_LaidLEAD_100.ogg","ref":[9,1319808,1332164]},{"name":"C_metallead_23.ogg","ref":[9,1332164,1344515]},{"name":"A_LaidLEAD_62.ogg","ref":[9,1344515,1356860]},{"name":"C_metallead_2.ogg","ref":[9,1356860,1369204]},{"name":"A_LaidLEAD_102.ogg","ref":[9,1369204,1381546]},{"name":"A_LaidLEAD_74.ogg","ref":[9,1381546,1393885]},{"name":"A_LaidLEAD_47.ogg","ref":[9,1393885,1406223]},{"name":"C_guitarsolo_37.ogg","ref":[9,1406223,1418559]},{"name":"A_laidbass_54.ogg","ref":[9,1418559,1430891]},{"name":"A_elecbass_7.ogg","ref":[9,1430891,1443221]},{"name":"A_lead1_109.ogg","ref":[9,1443221,1455550]},{"name":"A_laidbass_64.ogg","ref":[9,1455550,1467876]},{"name":"C_metallead_38.ogg","ref":[10,0,12326]},{"name":"A_acsnare_9.ogg","ref":[10,12326,24649]},{"name":"C_metallead_41.ogg","ref":[10,24649,36971]},{"name":"A_seclead_52.ogg","ref":[10,36971,49291]},{"name":"A_LaidLEAD_86.ogg","ref":[10,49291,61608]},{"name":"A_seclead_20.ogg","ref":[10,61608,73920]},{"name":"A_LaidLEAD_24.ogg","ref":[10,73920,86228]},{"name":"A_LaidLEAD_43.ogg","ref":[10,86228,98536]},{"name":"A_laidbass_3.ogg","ref":[10,98536,110842]},{"name":"A_elecbass_20.ogg","ref":[10,110842,123147]},{"name":"A_laidbass_34.ogg","ref":[10,123147,135451]},{"name":"A_laidbass_71.ogg","ref":[10,135451,147755]},{"name":"A_lead1_48.ogg","ref":[10,147755,160054]},{"name":"A_laidbass_41.ogg","ref":[10,160054,172349]},{"name":"A_LaidLEAD_4.ogg","ref":[10,172349,184640]},{"name":"A_elecbass_28.ogg","ref":[10,184640,196929]},{"name":"introlead_59.ogg","ref":[10,196929,209218]},{"name":"A_laidbass_84.ogg","ref":[10,209218,221506]},{"name":"A_elecbass_50.ogg","ref":[10,221506,233789]},{"name":"A_seclead_23.ogg","ref":[10,233789,246068]},{"name":"A_laidbass_91.ogg","ref":[10,246068,258346]},{"name":"A_seclead_34.ogg","ref":[10,258346,270623]},{"name":"A_seclead_15.ogg","ref":[10,270623,282897]},{"name":"A_elecbass_32.ogg","ref":[10,282897,295170]},{"name":"A_laidbass_82.ogg","ref":[10,295170,307442]},{"name":"A_lead1_41.ogg","ref":[10,307442,319711]},{"name":"A_synthstab_4.ogg","ref":[10,319711,331980]},{"name":"A_LaidLEAD_58.ogg","ref":[10,331980,344248]},{"name":"A_lead1_57.ogg","ref":[10,344248,356513]},{"name":"A_swinghat_3.ogg","ref":[10,356513,368778]},{"name":"A_Keys1_1.ogg","ref":[10,368778,381041]},{"name":"A_LaidLEAD_48.ogg","ref":[10,381041,393304]},{"name":"A_laidbass_5.ogg","ref":[10,393304,405564]},{"name":"A_laidbass_46.ogg","ref":[10,405564,417823]},{"name":"A_14basswav_58.ogg","ref":[10,417823,430077]},{"name":"A_seclead_49.ogg","ref":[10,430077,442331]},{"name":"A_laidbass_67.ogg","ref":[10,442331,454584]},{"name":"A_lead1_65.ogg","ref":[10,454584,466826]},{"name":"A_lead1_55.ogg","ref":[10,466826,479067]},{"name":"A_laidbass_7.ogg","ref":[10,479067,491306]},{"name":"A_LaidLEAD_46.ogg","ref":[10,491306,503541]},{"name":"A_laidbass_57.ogg","ref":[10,503541,515775]},{"name":"C_hats_7.ogg","ref":[10,515775,528008]},{"name":"C_crash_dld_2.ogg","ref":[10,528008,540240]},{"name":"A_LaidLEAD_85.ogg","ref":[10,540240,552471]},{"name":"A_pianosqstab_3.ogg","ref":[10,552471,564698]},{"name":"A_hihat_17.ogg","ref":[10,564698,576924]},{"name":"C_metallead_43.ogg","ref":[10,576924,589150]},{"name":"A_elecbass_15.ogg","ref":[10,589150,601374]},{"name":"C_metallead_68.ogg","ref":[10,601374,613591]},{"name":"A_lead1_81.ogg","ref":[10,613591,625807]},{"name":"A_laidbass_62.ogg","ref":[10,625807,638021]},{"name":"A_laidbass_42.ogg","ref":[10,638021,650232]},{"name":"A_laidbass_86.ogg","ref":[10,650232,662442]},{"name":"A_synthstab_2.ogg","ref":[10,662442,674646]},{"name":"A_acsnare_7.ogg","ref":[10,674646,686849]},{"name":"C_metallead_79.ogg","ref":[10,686849,699046]},{"name":"A_seclead_44.ogg","ref":[10,699046,711241]},{"name":"A_acsnare_6.ogg","ref":[10,711241,723435]},{"name":"A_LaidLEAD_56.ogg","ref":[10,723435,735625]},{"name":"A_lead1_8.ogg","ref":[10,735625,747812]},{"name":"A_LaidLEAD_34.ogg","ref":[10,747812,759997]},{"name":"A_laidbass_72.ogg","ref":[10,759997,772181]},{"name":"A_acsnare_13.ogg","ref":[10,772181,784363]},{"name":"A_LaidLEAD_77.ogg","ref":[10,784363,796544]},{"name":"A_synthstab_3.ogg","ref":[10,796544,808717]},{"name":"A_LaidLEAD_22.ogg","ref":[10,808717,820885]},{"name":"A_Keys1_13.ogg","ref":[10,820885,833052]},{"name":"A_laidbass_18.ogg","ref":[10,833052,845218]},{"name":"A_LaidLEAD_54.ogg","ref":[10,845218,857381]},{"name":"C_metallead_76.ogg","ref":[10,857381,869543]},{"name":"A_lead1_101.ogg","ref":[10,869543,881702]},{"name":"A_acsnare_4.ogg","ref":[10,881702,893860]},{"name":"A_seclead_5.ogg","ref":[10,893860,906017]},{"name":"C_metallead_14.ogg","ref":[10,906017,918174]},{"name":"introlead_63.ogg","ref":[10,918174,930327]},{"name":"A_elecbass_24.ogg","ref":[10,930327,942473]},{"name":"A_laidbass_10.ogg","ref":[10,942473,954618]},{"name":"introlead_6.ogg","ref":[10,954618,966763]},{"name":"introlead_19.ogg","ref":[10,966763,978907]},{"name":"A_elecbass_47.ogg","ref":[10,978907,991050]},{"name":"A_LaidLEAD_49.ogg","ref":[10,991050,1003192]},{"name":"A_Keys1_12.ogg","ref":[10,1003192,1015333]},{"name":"A_seclead_7.ogg","ref":[10,1015333,1027473]},{"name":"introlead_17.ogg","ref":[10,1027473,1039613]},{"name":"introlead_52.ogg","ref":[10,1039613,1051752]},{"name":"A_LaidLEAD_8.ogg","ref":[10,1051752,1063890]},{"name":"A_lead1_53.ogg","ref":[10,1063890,1076028]},{"name":"A_seclead_45.ogg","ref":[10,1076028,1088166]},{"name":"A_lead1_3.ogg","ref":[10,1088166,1100298]},{"name":"A_seclead_42.ogg","ref":[10,1100298,1112429]},{"name":"A_14basswav_33.ogg","ref":[10,1112429,1124557]},{"name":"inhale.ogg","ref":[10,1124557,1136685]},{"name":"introlead_57.ogg","ref":[10,1136685,1148808]},{"name":"A_LaidLEAD_66.ogg","ref":[10,1148808,1160927]},{"name":"A_lead1_14.ogg","ref":[10,1160927,1173043]},{"name":"A_laidbass_94.ogg","ref":[10,1173043,1185157]},{"name":"A_lead1_1.ogg","ref":[10,1185157,1197262]},{"name":"A_laidbass_70.ogg","ref":[10,1197262,1209366]},{"name":"A_laidbass_53.ogg","ref":[10,1209366,1221469]},{"name":"A_LaidLEAD_103.ogg","ref":[10,1221469,1233566]},{"name":"A_LaidLEAD_27.ogg","ref":[10,1233566,1245660]},{"name":"A_lead1_30.ogg","ref":[10,1245660,1257749]},{"name":"C_metallead_140.ogg","ref":[10,1257749,1269838]},{"name":"A_LaidLEAD_50.ogg","ref":[10,1269838,1281926]},{"name":"A_lead1_46.ogg","ref":[10,1281926,1294009]},{"name":"C_metallead_18.ogg","ref":[10,1294009,1306092]},{"name":"A_LaidLEAD_105.ogg","ref":[10,1306092,1318171]},{"name":"A_LaidLEAD_60.ogg","ref":[10,1318171,1330247]},{"name":"A_seclead_57.ogg","ref":[10,1330247,1342321]},{"name":"A_laidbass_59.ogg","ref":[10,1342321,1354393]},{"name":"A_lead1_15.ogg","ref":[10,1354393,1366463]},{"name":"A_laidbass_40.ogg","ref":[10,1366463,1378532]},{"name":"A_hihat_phr_1.ogg","ref":[10,1378532,1390597]},{"name":"A_LaidLEAD_61.ogg","ref":[10,1390597,1402662]},{"name":"A_LaidLEAD_14.ogg","ref":[10,1402662,1414724]},{"name":"A_lead1_98.ogg","ref":[10,1414724,1426785]},{"name":"A_lead1_147.ogg","ref":[10,1426785,1438844]},{"name":"C_guitarsolo_39.ogg","ref":[10,1438844,1450899]},{"name":"A_hihat_15.ogg","ref":[10,1450899,1462953]},{"name":"A_seclead_32.ogg","ref":[11,0,12054]},{"name":"A_lead1_75.ogg","ref":[11,12054,24104]},{"name":"A_seclead_16.ogg","ref":[11,24104,36154]},{"name":"stop.3.ogg","ref":[11,36154,48204]},{"name":"A_14basswav_96.ogg","ref":[11,48204,60252]},{"name":"A_elecbass_16.ogg","ref":[11,60252,72297]},{"name":"A_elecbass_8.ogg","ref":[11,72297,84342]},{"name":"A_laidbass_45.ogg","ref":[11,84342,96387]},{"name":"A_lead1_108.ogg","ref":[11,96387,108430]},{"name":"A_seclead_11.ogg","ref":[11,108430,120470]},{"name":"A_LaidLEAD_17.ogg","ref":[11,120470,132508]},{"name":"A_lead1_154.ogg","ref":[11,132508,144542]},{"name":"A_elecbass_14.ogg","ref":[11,144542,156574]},{"name":"A_lead1_12.ogg","ref":[11,156574,168605]},{"name":"A_LaidLEAD_18.ogg","ref":[11,168605,180634]},{"name":"A_LaidLEAD_25.ogg","ref":[11,180634,192663]},{"name":"C_metallead_161.ogg","ref":[11,192663,204689]},{"name":"C_metallead_19.ogg","ref":[11,204689,216708]},{"name":"A_laidbass_24.ogg","ref":[11,216708,228724]},{"name":"A_LaidLEAD_45.ogg","ref":[11,228724,240739]},{"name":"C_cymhdfill_10.ogg","ref":[11,240739,252753]},{"name":"A_LaidLEAD_55.ogg","ref":[11,252753,264766]},{"name":"A_LaidLEAD_88.ogg","ref":[11,264766,276779]},{"name":"A_lead1_69.ogg","ref":[11,276779,288792]},{"name":"introlead_36.ogg","ref":[11,288792,300803]},{"name":"A_laidbass_68.ogg","ref":[11,300803,312813]},{"name":"A_hihat_phr_4.ogg","ref":[11,312813,324822]},{"name":"A_LaidLEAD_32.ogg","ref":[11,324822,336829]},{"name":"A_LaidLEAD_96.ogg","ref":[11,336829,348836]},{"name":"C_guitarsolo_31.ogg","ref":[11,348836,360843]},{"name":"A_lead1_13.ogg","ref":[11,360843,372848]},{"name":"C_guitarsolo_17.ogg","ref":[11,372848,384853]},{"name":"A_14basswav_42.ogg","ref":[11,384853,396855]},{"name":"A_lead1_122.ogg","ref":[11,396855,408857]},{"name":"A_LaidLEAD_93.ogg","ref":[11,408857,420858]},{"name":"A_lead1_118.ogg","ref":[11,420858,432854]},{"name":"A_seclead_2.ogg","ref":[11,432854,444850]},{"name":"A_lead1_114.ogg","ref":[11,444850,456845]},{"name":"A_seclead_40.ogg","ref":[11,456845,468838]},{"name":"A_lead1_111.ogg","ref":[11,468838,480827]},{"name":"A_lead1_68.ogg","ref":[11,480827,492815]},{"name":"A_LaidLEAD_101.ogg","ref":[11,492815,504800]},{"name":"A_LaidLEAD_39.ogg","ref":[11,504800,516785]},{"name":"A_lead1_52.ogg","ref":[11,516785,528766]},{"name":"A_lead1_89.ogg","ref":[11,528766,540747]},{"name":"introlead_61.ogg","ref":[11,540747,552726]},{"name":"A_lead1_149.ogg","ref":[11,552726,564703]},{"name":"A_lead1_105.ogg","ref":[11,564703,576679]},{"name":"A_lead1_94.ogg","ref":[11,576679,588654]},{"name":"A_seclead_48.ogg","ref":[11,588654,600628]},{"name":"A_acsnare_24.ogg","ref":[11,600628,612601]},{"name":"A_LaidLEAD_21.ogg","ref":[11,612601,624574]},{"name":"A_lead1_26.ogg","ref":[11,624574,636546]},{"name":"A_lead1_72.ogg","ref":[11,636546,648517]},{"name":"A_laidbass_13.ogg","ref":[11,648517,660487]},{"name":"A_acsnare_1.ogg","ref":[11,660487,672456]},{"name":"A_lead1_152.ogg","ref":[11,672456,684425]},{"name":"A_lead1_42.ogg","ref":[11,684425,696391]},{"name":"A_seclead_33.ogg","ref":[11,696391,708357]},{"name":"A_lead1_116.ogg","ref":[11,708357,720321]},{"name":"A_laidbass_92.ogg","ref":[11,720321,732284]},{"name":"A_lead1_18.ogg","ref":[11,732284,744247]},{"name":"A_seclead_43.ogg","ref":[11,744247,756208]},{"name":"A_lead1_145.ogg","ref":[11,756208,768167]},{"name":"A_lead1_107.ogg","ref":[11,768167,780124]},{"name":"A_lead1_22.ogg","ref":[11,780124,792081]},{"name":"A_lead1_104.ogg","ref":[11,792081,804037]},{"name":"A_lead1_40.ogg","ref":[11,804037,815993]},{"name":"A_seclead_3.ogg","ref":[11,815993,827949]},{"name":"introlead_60.ogg","ref":[11,827949,839905]},{"name":"C_guitarsolo_13.ogg","ref":[11,839905,851860]},{"name":"A_lead1_73.ogg","ref":[11,851860,863813]},{"name":"A_lead1_119.ogg","ref":[11,863813,875765]},{"name":"A_seclead_17.ogg","ref":[11,875765,887717]},{"name":"A_seclead_12.ogg","ref":[11,887717,899668]},{"name":"A_LaidLEAD_15.ogg","ref":[11,899668,911618]},{"name":"A_swinghat_1.ogg","ref":[11,911618,923565]},{"name":"A_LaidLEAD_97.ogg","ref":[11,923565,935510]},{"name":"A_LaidLEAD_11.ogg","ref":[11,935510,947454]},{"name":"A_lead1_146.ogg","ref":[11,947454,959393]},{"name":"A_lead1_35.ogg","ref":[11,959393,971332]},{"name":"A_acsnare_20.ogg","ref":[11,971332,983270]},{"name":"A_LaidLEAD_33.ogg","ref":[11,983270,995205]},{"name":"A_LaidLEAD_13.ogg","ref":[11,995205,1007139]},{"name":"A_LaidLEAD_31.ogg","ref":[11,1007139,1019071]},{"name":"A_lead1_120.ogg","ref":[11,1019071,1031003]},{"name":"A_seclead_31.ogg","ref":[11,1031003,1042933]},{"name":"A_elecbass_40.ogg","ref":[11,1042933,1054861]},{"name":"introlead_28.ogg","ref":[11,1054861,1066786]},{"name":"A_LaidLEAD_84.ogg","ref":[11,1066786,1078710]},{"name":"A_LaidLEAD_99.ogg","ref":[11,1078710,1090633]},{"name":"A_lead1_100.ogg","ref":[11,1090633,1102556]},{"name":"introlead_62.ogg","ref":[11,1102556,1114478]},{"name":"C_metallead_165.ogg","ref":[11,1114478,1126396]},{"name":"A_elecbass_6.ogg","ref":[11,1126396,1138313]},{"name":"A_lead1_148.ogg","ref":[11,1138313,1150227]},{"name":"A_lead1_153.ogg","ref":[11,1150227,1162138]},{"name":"A_seclead_36.ogg","ref":[11,1162138,1174049]},{"name":"A_elecbass_3.ogg","ref":[11,1174049,1185959]},{"name":"A_LaidLEAD_110.ogg","ref":[11,1185959,1197866]},{"name":"A_lead1_99.ogg","ref":[11,1197866,1209772]},{"name":"A_seclead_41.ogg","ref":[11,1209772,1221678]},{"name":"A_hihat_phr_2.ogg","ref":[11,1221678,1233583]},{"name":"A_seclead_22.ogg","ref":[11,1233583,1245488]},{"name":"A_hihat_8.ogg","ref":[11,1245488,1257392]},{"name":"A_LaidLEAD_59.ogg","ref":[11,1257392,1269296]},{"name":"A_lead1_49.ogg","ref":[11,1269296,1281197]},{"name":"A_elecbass_45.ogg","ref":[11,1281197,1293097]},{"name":"A_LaidLEAD_104.ogg","ref":[11,1293097,1304996]},{"name":"A_lead1_10.ogg","ref":[11,1304996,1316894]},{"name":"A_LaidLEAD_28.ogg","ref":[11,1316894,1328791]},{"name":"A_lead1_47.ogg","ref":[11,1328791,1340686]},{"name":"A_14basswav_54.ogg","ref":[11,1340686,1352580]},{"name":"A_elecbass_36.ogg","ref":[11,1352580,1364474]},{"name":"A_elecbass_46.ogg","ref":[11,1364474,1376368]},{"name":"A_lead1_97.ogg","ref":[11,1376368,1388262]},{"name":"A_seclead_19.ogg","ref":[11,1388262,1400156]},{"name":"A_elecbass_11.ogg","ref":[11,1400156,1412047]},{"name":"A_elecbass_31.ogg","ref":[11,1412047,1423938]},{"name":"A_LaidLEAD_44.ogg","ref":[11,1423938,1435825]},{"name":"A_lead1_36.ogg","ref":[11,1435825,1447710]},{"name":"introlead_30.ogg","ref":[11,1447710,1459595]},{"name":"A_elecbass_22.ogg","ref":[11,1459595,1471478]},{"name":"A_elecbass_37.ogg","ref":[12,0,11881]},{"name":"C_metallead_129.ogg","ref":[12,11881,23762]},{"name":"A_seclead_6.ogg","ref":[12,23762,35642]},{"name":"A_elecbass_35.ogg","ref":[12,35642,47520]},{"name":"A_laidbass_76.ogg","ref":[12,47520,59397]},{"name":"introlead_41.ogg","ref":[12,59397,71274]},{"name":"A_LaidLEAD_41.ogg","ref":[12,71274,83149]},{"name":"C_metallead_39.ogg","ref":[12,83149,95024]},{"name":"A_elecbass_2.ogg","ref":[12,95024,106898]},{"name":"A_Keys1_3.ogg","ref":[12,106898,118772]},{"name":"A_elecbass_41.ogg","ref":[12,118772,130644]},{"name":"A_lead1_93.ogg","ref":[12,130644,142516]},{"name":"A_seclead_35.ogg","ref":[12,142516,154386]},{"name":"A_hihat_3.ogg","ref":[12,154386,166253]},{"name":"A_lead1_44.ogg","ref":[12,166253,178120]},{"name":"A_lead1_50.ogg","ref":[12,178120,189986]},{"name":"C_metallead_71.ogg","ref":[12,189986,201852]},{"name":"A_elecbass_39.ogg","ref":[12,201852,213717]},{"name":"introlead_40.ogg","ref":[12,213717,225581]},{"name":"A_seclead_39.ogg","ref":[12,225581,237443]},{"name":"C_hats_1.ogg","ref":[12,237443,249303]},{"name":"A_lead1_17.ogg","ref":[12,249303,261162]},{"name":"A_elecbass_42.ogg","ref":[12,261162,273019]},{"name":"A_lead1_16.ogg","ref":[12,273019,284875]},{"name":"A_Keys1_4.ogg","ref":[12,284875,296730]},{"name":"introlead_4.ogg","ref":[12,296730,308585]},{"name":"C_metallead_21.ogg","ref":[12,308585,320439]},{"name":"A_laidbass_89.ogg","ref":[12,320439,332290]},{"name":"A_seclead_10.ogg","ref":[12,332290,344141]},{"name":"A_hihat_14.ogg","ref":[12,344141,355991]},{"name":"A_seclead_51.ogg","ref":[12,355991,367841]},{"name":"C_metallead_37.ogg","ref":[12,367841,379691]},{"name":"A_14basswav_45.ogg","ref":[12,379691,391540]},{"name":"A_hihat_11.ogg","ref":[12,391540,403388]},{"name":"C_metallead_78.ogg","ref":[12,403388,415232]},{"name":"introlead_54.ogg","ref":[12,415232,427076]},{"name":"C_crash_dld_3.ogg","ref":[12,427076,438918]},{"name":"C_guitarsolo_5.ogg","ref":[12,438918,450760]},{"name":"A_hihat_phr_12.ogg","ref":[12,450760,462601]},{"name":"introlead_8.ogg","ref":[12,462601,474442]},{"name":"A_LaidLEAD_38.ogg","ref":[12,474442,486281]},{"name":"C_guitarsolo_35.ogg","ref":[12,486281,498120]},{"name":"A_LaidLEAD_19.ogg","ref":[12,498120,509957]},{"name":"A_hihat_phr_10.ogg","ref":[12,509957,521793]},{"name":"B_stupiano_8.ogg","ref":[12,521793,533626]},{"name":"A_LaidLEAD_109.ogg","ref":[12,533626,545458]},{"name":"A_LaidLEAD_2.ogg","ref":[12,545458,557290]},{"name":"A_seclead_47.ogg","ref":[12,557290,569120]},{"name":"introlead_49.ogg","ref":[12,569120,580948]},{"name":"A_14basswav_36.ogg","ref":[12,580948,592774]},{"name":"A_seclead_18.ogg","ref":[12,592774,604600]},{"name":"A_seclead_13.ogg","ref":[12,604600,616425]},{"name":"C_cymhdfill_1.ogg","ref":[12,616425,628250]},{"name":"C_metallead_69.ogg","ref":[12,628250,640075]},{"name":"introlead_39.ogg","ref":[12,640075,651898]},{"name":"A_Keys1_21.ogg","ref":[12,651898,663719]},{"name":"introlead_50.ogg","ref":[12,663719,675540]},{"name":"C_metallead_40.ogg","ref":[12,675540,687360]},{"name":"introlead_43.ogg","ref":[12,687360,699180]},{"name":"A_LaidLEAD_37.ogg","ref":[12,699180,710997]},{"name":"C_metallead_10.ogg","ref":[12,710997,722813]},{"name":"A_laidbass_65.ogg","ref":[12,722813,734628]},{"name":"C_guitarsolo_22.ogg","ref":[12,734628,746443]},{"name":"C_metallead_20.ogg","ref":[12,746443,758258]},{"name":"A_14basswav_28.ogg","ref":[12,758258,770072]},{"name":"A_elecbass_17.ogg","ref":[12,770072,781886]},{"name":"A_lead1_37.ogg","ref":[12,781886,793698]},{"name":"C_metallead_30.ogg","ref":[12,793698,805510]},{"name":"A_LaidLEAD_20.ogg","ref":[12,805510,817319]},{"name":"introlead_51.ogg","ref":[12,817319,829128]},{"name":"A_acsnare_21.ogg","ref":[12,829128,840936]},{"name":"A_lead1_11.ogg","ref":[12,840936,852742]},{"name":"C_metallead_107.ogg","ref":[12,852742,864548]},{"name":"C_metallead_13.ogg","ref":[12,864548,876353]},{"name":"C_metallead_104.ogg","ref":[12,876353,888157]},{"name":"A_LaidLEAD_94.ogg","ref":[12,888157,899960]},{"name":"C_cymhdfill_2.ogg","ref":[12,899960,911761]},{"name":"A_14basswav_27.ogg","ref":[12,911761,923558]},{"name":"A_14basswav_92.ogg","ref":[12,923558,935352]},{"name":"C_crash_basic.ogg","ref":[12,935352,947146]},{"name":"A_hihat_4.ogg","ref":[12,947146,958939]},{"name":"stop.1.ogg","ref":[12,958939,970732]},{"name":"C_metallead_143.ogg","ref":[12,970732,982523]},{"name":"A_LaidLEAD_52.ogg","ref":[12,982523,994313]},{"name":"A_seclead_37.ogg","ref":[12,994313,1006102]},{"name":"C_guitarsolo_8.ogg","ref":[12,1006102,1017888]},{"name":"C_metallead_3.ogg","ref":[12,1017888,1029674]},{"name":"introlead_26.ogg","ref":[12,1029674,1041459]},{"name":"C_metallead_29.ogg","ref":[12,1041459,1053243]},{"name":"A_LaidLEAD_95.ogg","ref":[12,1053243,1065026]},{"name":"C_guitarsolo_9.ogg","ref":[12,1065026,1076809]},{"name":"A_laidbass_47.ogg","ref":[12,1076809,1088591]},{"name":"C_metallead_157.ogg","ref":[12,1088591,1100373]},{"name":"C_metallead_49.ogg","ref":[12,1100373,1112155]},{"name":"A_LaidLEAD_83.ogg","ref":[12,1112155,1123936]},{"name":"A_LaidLEAD_53.ogg","ref":[12,1123936,1135716]},{"name":"A_14basswav_74.ogg","ref":[12,1135716,1147495]},{"name":"A_lead1_38.ogg","ref":[12,1147495,1159273]},{"name":"A_minitom_1.ogg","ref":[12,1159273,1171049]},{"name":"B_piano56.ogg","ref":[12,1171049,1182825]},{"name":"C_metallead_27.ogg","ref":[12,1182825,1194600]},{"name":"A_elecbass_43.ogg","ref":[12,1194600,1206373]},{"name":"A_Keys1_9.ogg","ref":[12,1206373,1218146]},{"name":"A_hihat_10.ogg","ref":[12,1218146,1229918]},{"name":"A_swinghat_2.ogg","ref":[12,1229918,1241689]},{"name":"A_seclead_9.ogg","ref":[12,1241689,1253459]},{"name":"A_elecbass_18.ogg","ref":[12,1253459,1265228]},{"name":"C_guitarsolo_24.ogg","ref":[12,1265228,1276997]},{"name":"C_metallead_103.ogg","ref":[12,1276997,1288766]},{"name":"stab_2.ogg","ref":[12,1288766,1300534]},{"name":"A_seclead_28.ogg","ref":[12,1300534,1312299]},{"name":"A_14basswav_2.ogg","ref":[12,1312299,1324063]},{"name":"A_LaidLEAD_40.ogg","ref":[12,1324063,1335827]},{"name":"A_LaidLEAD_69.ogg","ref":[12,1335827,1347590]},{"name":"A_seclead_38.ogg","ref":[12,1347590,1359352]},{"name":"A_14basswav_14.ogg","ref":[12,1359352,1371113]},{"name":"A_seclead_4.ogg","ref":[12,1371113,1382873]},{"name":"C_metallead_116.ogg","ref":[12,1382873,1394629]},{"name":"C_guitarsolo_25.ogg","ref":[12,1394629,1406384]},{"name":"C_metallead_159.ogg","ref":[12,1406384,1418139]},{"name":"C_metallead_24.ogg","ref":[12,1418139,1429892]},{"name":"C_metallead_100.ogg","ref":[12,1429892,1441643]},{"name":"A_lead1_102.ogg","ref":[12,1441643,1453393]},{"name":"A_seclead_30.ogg","ref":[12,1453393,1465143]},{"name":"A_14basswav_23.ogg","ref":[13,0,11749]},{"name":"C_guitarsolo_26.ogg","ref":[13,11749,23498]},{"name":"C_metallead_109.ogg","ref":[13,23498,35245]},{"name":"A_LaidLEAD_68.ogg","ref":[13,35245,46991]},{"name":"A_14basswav_89.ogg","ref":[13,46991,58736]},{"name":"C_metallead_55.ogg","ref":[13,58736,70479]},{"name":"A_lead1_124.ogg","ref":[13,70479,82221]},{"name":"A_lead1_126.ogg","ref":[13,82221,93963]},{"name":"A_lead1_34.ogg","ref":[13,93963,105705]},{"name":"A_elecbass_1.ogg","ref":[13,105705,117446]},{"name":"B_stupiano_6.ogg","ref":[13,117446,129187]},{"name":"C_metallead_156.ogg","ref":[13,129187,140927]},{"name":"A_lead1_23.ogg","ref":[13,140927,152666]},{"name":"A_lead1_25.ogg","ref":[13,152666,164405]},{"name":"A_lead1_9.ogg","ref":[13,164405,176144]},{"name":"C_guitarsolo_2.ogg","ref":[13,176144,187883]},{"name":"C_guitarsolo_7.ogg","ref":[13,187883,199620]},{"name":"C_metallead_106.ogg","ref":[13,199620,211357]},{"name":"A_elecbass_10.ogg","ref":[13,211357,223093]},{"name":"introlead_24.ogg","ref":[13,223093,234829]},{"name":"A_elecbass_26.ogg","ref":[13,234829,246564]},{"name":"A_lead1_151.ogg","ref":[13,246564,258299]},{"name":"C_metallead_52.ogg","ref":[13,258299,270033]},{"name":"A_hihat_phr_9.ogg","ref":[13,270033,281766]},{"name":"introlead_9.ogg","ref":[13,281766,293499]},{"name":"C_metallead_158.ogg","ref":[13,293499,305231]},{"name":"C_metallead_70.ogg","ref":[13,305231,316963]},{"name":"A_hihat_phr_8.ogg","ref":[13,316963,328694]},{"name":"C_metallead_12.ogg","ref":[13,328694,340425]},{"name":"C_metallead_51.ogg","ref":[13,340425,352156]},{"name":"C_metallead_117.ogg","ref":[13,352156,363886]},{"name":"C_metallead_17.ogg","ref":[13,363886,375616]},{"name":"A_lead1_132.ogg","ref":[13,375616,387344]},{"name":"A_hihat_6.ogg","ref":[13,387344,399071]},{"name":"A_lead1_27.ogg","ref":[13,399071,410798]},{"name":"B_piano59.ogg","ref":[13,410798,422525]},{"name":"C_cymhdfill_9.ogg","ref":[13,422525,434252]},{"name":"A_14basswav_29.ogg","ref":[13,434252,445978]},{"name":"A_14basswav_84.ogg","ref":[13,445978,457704]},{"name":"C_metallead_138.ogg","ref":[13,457704,469430]},{"name":"C_metallead_22.ogg","ref":[13,469430,481156]},{"name":"A_elecbass_9.ogg","ref":[13,481156,492881]},{"name":"A_hihat_phr_3.ogg","ref":[13,492881,504604]},{"name":"A_lead1_66.ogg","ref":[13,504604,516326]},{"name":"C_metallead_4.ogg","ref":[13,516326,528048]},{"name":"A_acsnare_10.ogg","ref":[13,528048,539769]},{"name":"C_metallead_113.ogg","ref":[13,539769,551489]},{"name":"C_metallead_96.ogg","ref":[13,551489,563208]},{"name":"C_guitarsolo_12.ogg","ref":[13,563208,574926]},{"name":"C_metallead_46.ogg","ref":[13,574926,586644]},{"name":"introlead_44.ogg","ref":[13,586644,598362]},{"name":"A_LaidLEAD_23.ogg","ref":[13,598362,610075]},{"name":"A_seclead_1.ogg","ref":[13,610075,621788]},{"name":"A_hihat_phr_7.ogg","ref":[13,621788,633500]},{"name":"C_metallead_11.ogg","ref":[13,633500,645211]},{"name":"A_14basswav_30.ogg","ref":[13,645211,656921]},{"name":"A_acsnare_2.ogg","ref":[13,656921,668631]},{"name":"C_metallead_1.ogg","ref":[13,668631,680340]},{"name":"C_metallead_63.ogg","ref":[13,680340,692049]},{"name":"C_metallead_61.ogg","ref":[13,692049,703757]},{"name":"A_LaidLEAD_98.ogg","ref":[13,703757,715463]},{"name":"C_metallead_97.ogg","ref":[13,715463,727169]},{"name":"A_lead1_29.ogg","ref":[13,727169,738874]},{"name":"C_metallead_15.ogg","ref":[13,738874,750579]},{"name":"A_lead1_131.ogg","ref":[13,750579,762282]},{"name":"C_metallead_114.ogg","ref":[13,762282,773985]},{"name":"C_metallead_132.ogg","ref":[13,773985,785688]},{"name":"A_elecbass_12.ogg","ref":[13,785688,797390]},{"name":"C_metallead_149.ogg","ref":[13,797390,809092]},{"name":"C_metallead_28.ogg","ref":[13,809092,820793]},{"name":"C_metallead_102.ogg","ref":[13,820793,832493]},{"name":"C_metallead_144.ogg","ref":[13,832493,844193]},{"name":"introlead_45.ogg","ref":[13,844193,855893]},{"name":"A_14basswav_4.ogg","ref":[13,855893,867592]},{"name":"A_LaidLEAD_78.ogg","ref":[13,867592,879291]},{"name":"C_metallead_54.ogg","ref":[13,879291,890989]},{"name":"introlead_55.ogg","ref":[13,890989,902687]},{"name":"A_hihat_phr_11.ogg","ref":[13,902687,914384]},{"name":"A_lead1_31.ogg","ref":[13,914384,926081]},{"name":"A_seclead_54.ogg","ref":[13,926081,937778]},{"name":"C_metallead_45.ogg","ref":[13,937778,949473]},{"name":"C_metallead_147.ogg","ref":[13,949473,961167]},{"name":"introlead_15.ogg","ref":[13,961167,972859]},{"name":"A_14basswav_95.ogg","ref":[13,972859,984550]},{"name":"C_metallead_44.ogg","ref":[13,984550,996240]},{"name":"A_14basswav_98.ogg","ref":[13,996240,1007929]},{"name":"A_acsnare_12.ogg","ref":[13,1007929,1019618]},{"name":"A_Keys1_19.ogg","ref":[13,1019618,1031307]},{"name":"A_lead1_128.ogg","ref":[13,1031307,1042996]},{"name":"C_cymhdfill_5.ogg","ref":[13,1042996,1054685]},{"name":"C_metallead_142.ogg","ref":[13,1054685,1066373]},{"name":"C_metallead_56.ogg","ref":[13,1066373,1078061]},{"name":"A_14basswav_38.ogg","ref":[13,1078061,1089748]},{"name":"introlead_46.ogg","ref":[13,1089748,1101435]},{"name":"C_guitarsolo_23.ogg","ref":[13,1101435,1113121]},{"name":"C_metallead_101.ogg","ref":[13,1113121,1124807]},{"name":"A_lead1_138.ogg","ref":[13,1124807,1136492]},{"name":"A_seclead_56.ogg","ref":[13,1136492,1148177]},{"name":"A_LaidLEAD_7.ogg","ref":[13,1148177,1159861]},{"name":"C_metallead_83.ogg","ref":[13,1159861,1171544]},{"name":"C_metallead_154.ogg","ref":[13,1171544,1183226]},{"name":"introlead_42.ogg","ref":[13,1183226,1194908]},{"name":"C_metallead_84.ogg","ref":[13,1194908,1206587]},{"name":"A_14basswav_77.ogg","ref":[13,1206587,1218265]},{"name":"A_acsnare_11.ogg","ref":[13,1218265,1229942]},{"name":"A_seclead_27.ogg","ref":[13,1229942,1241619]},{"name":"C_metallead_82.ogg","ref":[13,1241619,1253296]},{"name":"A_hihat_9.ogg","ref":[13,1253296,1264972]},{"name":"A_LaidLEAD_63.ogg","ref":[13,1264972,1276647]},{"name":"A_lead1_133.ogg","ref":[13,1276647,1288322]},{"name":"C_metallead_141.ogg","ref":[13,1288322,1299997]},{"name":"A_hihat_5.ogg","ref":[13,1299997,1311670]},{"name":"C_metallead_148.ogg","ref":[13,1311670,1323343]},{"name":"introlead_18.ogg","ref":[13,1323343,1335016]},{"name":"C_guitarsolo_20.ogg","ref":[13,1335016,1346688]},{"name":"C_metallead_94.ogg","ref":[13,1346688,1358360]},{"name":"A_swinghat_5.ogg","ref":[13,1358360,1370031]},{"name":"C_metallead_26.ogg","ref":[13,1370031,1381702]},{"name":"C_metallead_60.ogg","ref":[13,1381702,1393373]},{"name":"A_acsnare_25.ogg","ref":[13,1393373,1405043]},{"name":"C_metallead_137.ogg","ref":[13,1405043,1416713]},{"name":"A_lead1_86.ogg","ref":[13,1416713,1428382]},{"name":"A_shaker 4.ogg","ref":[13,1428382,1440051]},{"name":"C_metallead_119.ogg","ref":[13,1440051,1451720]},{"name":"C_metallead_120.ogg","ref":[13,1451720,1463389]},{"name":"A_lead1_91.ogg","ref":[14,0,11668]},{"name":"C_metallead_33.ogg","ref":[14,11668,23335]},{"name":"C_metallead_7.ogg","ref":[14,23335,35002]},{"name":"A_LaidLEAD_87.ogg","ref":[14,35002,46668]},{"name":"A_seclead_29.ogg","ref":[14,46668,58334]},{"name":"C_metallead_121.ogg","ref":[14,58334,69999]},{"name":"A_hihat_16.ogg","ref":[14,69999,81662]},{"name":"A_lead1_78.ogg","ref":[14,81662,93325]},{"name":"C_metallead_9.ogg","ref":[14,93325,104988]},{"name":"A_lead1_64.ogg","ref":[14,104988,116650]},{"name":"C_metallead_123.ogg","ref":[14,116650,128311]},{"name":"C_metallead_108.ogg","ref":[14,128311,139971]},{"name":"introlead_27.ogg","ref":[14,139971,151630]},{"name":"C_metallead_155.ogg","ref":[14,151630,163288]},{"name":"A_hihat_phr_6.ogg","ref":[14,163288,174945]},{"name":"C_cymhdfill_8.ogg","ref":[14,174945,186601]},{"name":"A_LaidLEAD_35.ogg","ref":[14,186601,198256]},{"name":"B_piano57.ogg","ref":[14,198256,209911]},{"name":"C_metallead_81.ogg","ref":[14,209911,221566]},{"name":"C_metallead_111.ogg","ref":[14,221566,233220]},{"name":"C_metallead_32.ogg","ref":[14,233220,244874]},{"name":"C_metallead_65.ogg","ref":[14,244874,256528]},{"name":"A_hihat_13.ogg","ref":[14,256528,268181]},{"name":"A_LaidLEAD_64.ogg","ref":[14,268181,279834]},{"name":"A_lead1_130.ogg","ref":[14,279834,291487]},{"name":"A_seclead_50.ogg","ref":[14,291487,303140]},{"name":"A_elecbass_4.ogg","ref":[14,303140,314792]},{"name":"A_lead1_135.ogg","ref":[14,314792,326444]},{"name":"C_guitarsolo_34.ogg","ref":[14,326444,338096]},{"name":"C_metallead_135.ogg","ref":[14,338096,349748]},{"name":"C_metallead_153.ogg","ref":[14,349748,361400]},{"name":"introlead_12.ogg","ref":[14,361400,373052]},{"name":"C_metallead_112.ogg","ref":[14,373052,384702]},{"name":"C_metallead_93.ogg","ref":[14,384702,396352]},{"name":"C_metallead_152.ogg","ref":[14,396352,408001]},{"name":"C_metallead_160.ogg","ref":[14,408001,419650]},{"name":"A_elecbass_30.ogg","ref":[14,419650,431297]},{"name":"C_metallead_124.ogg","ref":[14,431297,442943]},{"name":"C_metallead_90.ogg","ref":[14,442943,454589]},{"name":"introlead_25.ogg","ref":[14,454589,466235]},{"name":"C_metallead_136.ogg","ref":[14,466235,477879]},{"name":"C_metallead_36.ogg","ref":[14,477879,489523]},{"name":"introlead_32.ogg","ref":[14,489523,501167]},{"name":"A_LaidLEAD_16.ogg","ref":[14,501167,512810]},{"name":"A_seclead_26.ogg","ref":[14,512810,524453]},{"name":"C_metallead_75.ogg","ref":[14,524453,536096]},{"name":"A_LaidLEAD_9.ogg","ref":[14,536096,547738]},{"name":"C_metallead_105.ogg","ref":[14,547738,559379]},{"name":"C_metallead_31.ogg","ref":[14,559379,571020]},{"name":"A_lead1_137.ogg","ref":[14,571020,582660]},{"name":"A_lead1_82.ogg","ref":[14,582660,594300]},{"name":"C_metallead_118.ogg","ref":[14,594300,605940]},{"name":"A_14basswav_49.ogg","ref":[14,605940,617579]},{"name":"A_LaidLEAD_67.ogg","ref":[14,617579,629218]},{"name":"C_metallead_48.ogg","ref":[14,629218,640856]},{"name":"A_acsnare_16.ogg","ref":[14,640856,652493]},{"name":"A_seclead_53.ogg","ref":[14,652493,664130]},{"name":"C_metallead_64.ogg","ref":[14,664130,675766]},{"name":"A_lead1_123.ogg","ref":[14,675766,687401]},{"name":"C_metallead_115.ogg","ref":[14,687401,699036]},{"name":"C_cymhdfill_4.ogg","ref":[14,699036,710669]},{"name":"A_14basswav_99.ogg","ref":[14,710669,722301]},{"name":"A_lead1_115.ogg","ref":[14,722301,733933]},{"name":"C_metallead_85.ogg","ref":[14,733933,745565]},{"name":"C_cymhdfill_3.ogg","ref":[14,745565,757196]},{"name":"C_metallead_50.ogg","ref":[14,757196,768827]},{"name":"A_LaidLEAD_30.ogg","ref":[14,768827,780457]},{"name":"A_lead1_83.ogg","ref":[14,780457,792087]},{"name":"C_metallead_95.ogg","ref":[14,792087,803717]},{"name":"A_14basswav_35.ogg","ref":[14,803717,815346]},{"name":"A_seclead_55.ogg","ref":[14,815346,826975]},{"name":"C_metallead_110.ogg","ref":[14,826975,838604]},{"name":"C_metallead_91.ogg","ref":[14,838604,850231]},{"name":"C_metallead_16.ogg","ref":[14,850231,861857]},{"name":"A_LaidLEAD_6.ogg","ref":[14,861857,873482]},{"name":"C_metallead_122.ogg","ref":[14,873482,885107]},{"name":"C_metallead_89.ogg","ref":[14,885107,896732]},{"name":"A_lead1_136.ogg","ref":[14,896732,908353]},{"name":"A_lead1_144.ogg","ref":[14,908353,919974]},{"name":"C_cymhdfill_7.ogg","ref":[14,919974,931595]},{"name":"C_metallead_42.ogg","ref":[14,931595,943216]},{"name":"A_14basswav_88.ogg","ref":[14,943216,954836]},{"name":"A_acsnare_17.ogg","ref":[14,954836,966456]},{"name":"A_LaidLEAD_70.ogg","ref":[14,966456,978076]},{"name":"A_lead1_125.ogg","ref":[14,978076,989696]},{"name":"introlead_48.ogg","ref":[14,989696,1001316]},{"name":"A_lead1_87.ogg","ref":[14,1001316,1012935]},{"name":"C_metallead_150.ogg","ref":[14,1012935,1024554]},{"name":"C_guitarsolo_28.ogg","ref":[14,1024554,1036172]},{"name":"C_metallead_146.ogg","ref":[14,1036172,1047790]},{"name":"A_seclead_24.ogg","ref":[14,1047790,1059407]},{"name":"C_metallead_134.ogg","ref":[14,1059407,1071024]},{"name":"C_metallead_5.ogg","ref":[14,1071024,1082641]},{"name":"A_14basswav_97.ogg","ref":[14,1082641,1094257]},{"name":"B_piano58.ogg","ref":[14,1094257,1105873]},{"name":"A_lead1_77.ogg","ref":[14,1105873,1117488]},{"name":"C_metallead_163.ogg","ref":[14,1117488,1129103]},{"name":"A_14basswav_81.ogg","ref":[14,1129103,1140717]},{"name":"A_lead1_142.ogg","ref":[14,1140717,1152331]},{"name":"C_metallead_164.ogg","ref":[14,1152331,1163945]},{"name":"A_lead1_24.ogg","ref":[14,1163945,1175558]},{"name":"C_metallead_53.ogg","ref":[14,1175558,1187171]},{"name":"A_lead1_134.ogg","ref":[14,1187171,1198783]},{"name":"A_laidbass_102.ogg","ref":[14,1198783,1210394]},{"name":"A_LaidLEAD_65.ogg","ref":[14,1210394,1222005]},{"name":"introlead_5.ogg","ref":[14,1222005,1233614]},{"name":"A_lead1_32.ogg","ref":[14,1233614,1245222]},{"name":"C_metallead_8.ogg","ref":[14,1245222,1256829]},{"name":"A_14basswav_90.ogg","ref":[14,1256829,1268435]},{"name":"C_cymhdfill_11.ogg","ref":[14,1268435,1280041]},{"name":"C_metallead_139.ogg","ref":[14,1280041,1291647]},{"name":"introlead_47.ogg","ref":[14,1291647,1303253]},{"name":"A_lead1_139.ogg","ref":[14,1303253,1314858]},{"name":"A_lead1_84.ogg","ref":[14,1314858,1326462]},{"name":"C_guitarsolo_36.ogg","ref":[14,1326462,1338066]},{"name":"C_metallead_74.ogg","ref":[14,1338066,1349670]},{"name":"A_acsnare_23.ogg","ref":[14,1349670,1361273]},{"name":"A_laidbass_50.ogg","ref":[14,1361273,1372874]},{"name":"A_lead1_113.ogg","ref":[14,1372874,1384475]},{"name":"A_lead1_79.ogg","ref":[14,1384475,1396076]},{"name":"C_guitarsolo_30.ogg","ref":[14,1396076,1407677]},{"name":"C_metallead_92.ogg","ref":[14,1407677,1419278]},{"name":"A_seclead_8.ogg","ref":[14,1419278,1430878]},{"name":"A_acsnare_15.ogg","ref":[14,1430878,1442476]},{"name":"C_metallead_35.ogg","ref":[14,1442476,1454074]},{"name":"A_lead1_127.ogg","ref":[14,1454074,1465671]},{"name":"A_lead1_85.ogg","ref":[15,0,11597]},{"name":"A_seclead_14.ogg","ref":[15,11597,23194]},{"name":"A_LaidLEAD_75.ogg","ref":[15,23194,34790]},{"name":"A_lead1_76.ogg","ref":[15,34790,46386]},{"name":"C_guitarsolo_3.ogg","ref":[15,46386,57981]},{"name":"C_metallead_73.ogg","ref":[15,57981,69575]},{"name":"A_lead1_150.ogg","ref":[15,69575,81168]},{"name":"C_metallead_59.ogg","ref":[15,81168,92761]},{"name":"A_elecbass_29.ogg","ref":[15,92761,104353]},{"name":"C_metallead_6.ogg","ref":[15,104353,115945]},{"name":"C_metallead_72.ogg","ref":[15,115945,127537]},{"name":"A_lead1_71.ogg","ref":[15,127537,139127]},{"name":"introlead_13.ogg","ref":[15,139127,150717]},{"name":"A_lead1_28.ogg","ref":[15,150717,162306]},{"name":"C_metallead_66.ogg","ref":[15,162306,173895]},{"name":"introlead_11.ogg","ref":[15,173895,185483]},{"name":"A_14basswav_48.ogg","ref":[15,185483,197070]},{"name":"C_metallead_86.ogg","ref":[15,197070,208657]},{"name":"A_lead1_20.ogg","ref":[15,208657,220243]},{"name":"A_lead1_70.ogg","ref":[15,220243,231829]},{"name":"C_metallead_25.ogg","ref":[15,231829,243412]},{"name":"C_metallead_88.ogg","ref":[15,243412,254995]},{"name":"A_lead1_19.ogg","ref":[15,254995,266576]},{"name":"A_seclead_21.ogg","ref":[15,266576,278157]},{"name":"A_LaidLEAD_10.ogg","ref":[15,278157,289737]},{"name":"A_LaidLEAD_12.ogg","ref":[15,289737,301317]},{"name":"introlead_34.ogg","ref":[15,301317,312896]},{"name":"C_metallead_151.ogg","ref":[15,312896,324474]},{"name":"C_metallead_34.ogg","ref":[15,324474,336052]},{"name":"introlead_23.ogg","ref":[15,336052,347629]},{"name":"A_lead1_112.ogg","ref":[15,347629,359205]},{"name":"A_lead1_96.ogg","ref":[15,359205,370779]},{"name":"C_metallead_126.ogg","ref":[15,370779,382351]},{"name":"A_lead1_21.ogg","ref":[15,382351,393921]},{"name":"A_lead1_129.ogg","ref":[15,393921,405490]},{"name":"C_cymhdfill_6.ogg","ref":[15,405490,417057]},{"name":"A_14basswav_43.ogg","ref":[15,417057,428623]},{"name":"C_metallead_145.ogg","ref":[15,428623,440189]},{"name":"A_lead1_33.ogg","ref":[15,440189,451754]},{"name":"A_lead1_74.ogg","ref":[15,451754,463319]},{"name":"A_lead1_121.ogg","ref":[15,463319,474883]},{"name":"A_lead1_88.ogg","ref":[15,474883,486447]},{"name":"A_14basswav_65.ogg","ref":[15,486447,498010]},{"name":"A_lead1_143.ogg","ref":[15,498010,509573]},{"name":"C_metallead_87.ogg","ref":[15,509573,521136]},{"name":"A_14basswav_31.ogg","ref":[15,521136,532697]},{"name":"A_seclead_25.ogg","ref":[15,532697,544256]},{"name":"A_Keys1_16.ogg","ref":[15,544256,555814]},{"name":"C_metallead_58.ogg","ref":[15,555814,567372]},{"name":"A_14basswav_76.ogg","ref":[15,567372,578929]},{"name":"A_acsnare_18.ogg","ref":[15,578929,590486]},{"name":"C_metallead_47.ogg","ref":[15,590486,602043]},{"name":"A_14basswav_82.ogg","ref":[15,602043,613597]},{"name":"A_LaidLEAD_89.ogg","ref":[15,613597,625151]},{"name":"A_lead1_141.ogg","ref":[15,625151,636704]},{"name":"C_metallead_57.ogg","ref":[15,636704,648257]},{"name":"A_LaidLEAD_107.ogg","ref":[15,648257,659808]},{"name":"C_metallead_125.ogg","ref":[15,659808,671359]},{"name":"introlead_20.ogg","ref":[15,671359,682909]},{"name":"A_lead1_117.ogg","ref":[15,682909,694457]},{"name":"A_elecbass_44.ogg","ref":[15,694457,706004]},{"name":"A_lead1_140.ogg","ref":[15,706004,717551]},{"name":"C_guitarsolo_19.ogg","ref":[15,717551,729098]},{"name":"A_synthstab_5.ogg","ref":[15,729098,740644]},{"name":"A_LaidLEAD_1.ogg","ref":[15,740644,752188]},{"name":"A_lead1_90.ogg","ref":[15,752188,763732]},{"name":"C_guitarsolo_21.ogg","ref":[15,763732,775276]},{"name":"A_LaidLEAD_3.ogg","ref":[15,775276,786819]},{"name":"A_elecbass_5.ogg","ref":[15,786819,798360]},{"name":"introlead_21.ogg","ref":[15,798360,809900]},{"name":"C_metallead_131.ogg","ref":[15,809900,821435]},{"name":"A_lead1_67.ogg","ref":[15,821435,832969]},{"name":"A_synthstab_8.ogg","ref":[15,832969,844491]},{"name":"C_guitarsolo_6.ogg","ref":[15,844491,856011]},{"name":"A_lead1_80.ogg","ref":[15,856011,867529]},{"name":"A_acsnare_19.ogg","ref":[15,867529,879045]},{"name":"A_Keys1_7.ogg","ref":[15,879045,890560]},{"name":"A_elecbass_38.ogg","ref":[15,890560,902074]},{"name":"A_Keys1_6.ogg","ref":[15,902074,913587]},{"name":"A_lead1_43.ogg","ref":[15,913587,925100]},{"name":"A_LaidLEAD_108.ogg","ref":[15,925100,936607]},{"name":"A_lead1_92.ogg","ref":[15,936607,948113]},{"name":"A_lead1_103.ogg","ref":[15,948113,959612]},{"name":"A_synthstab_1.ogg","ref":[15,959612,971108]},{"name":"A_lead1_106.ogg","ref":[15,971108,982601]},{"name":"A_LaidLEAD_71.ogg","ref":[15,982601,994091]},{"name":"A_14basswav_102.ogg","ref":[15,994091,1005580]},{"name":"A_elecbass_27.ogg","ref":[15,1005580,1017068]},{"name":"B_stupiano_10.ogg","ref":[15,1017068,1028555]},{"name":"introlead_29.ogg","ref":[15,1028555,1040042]},{"name":"C_hats_8.ogg","ref":[15,1040042,1051528]},{"name":"A_14basswav_46.ogg","ref":[15,1051528,1063013]},{"name":"A_synthstab_7.ogg","ref":[15,1063013,1074497]},{"name":"introlead_14.ogg","ref":[15,1074497,1085981]},{"name":"C_guitarsolo_18.ogg","ref":[15,1085981,1097464]},{"name":"C_hats_10.ogg","ref":[15,1097464,1108941]},{"name":"B_piano60.ogg","ref":[15,1108941,1120413]},{"name":"A_synthstab_6.ogg","ref":[15,1120413,1131883]},{"name":"C_guitarsolo_11.ogg","ref":[15,1131883,1143353]},{"name":"A_Keys1_14.ogg","ref":[15,1143353,1154815]},{"name":"A_14basswav_50.ogg","ref":[15,1154815,1166273]},{"name":"A_Keys1_5.ogg","ref":[15,1166273,1177726]},{"name":"C_metallead_127.ogg","ref":[15,1177726,1189179]},{"name":"introlead_53.ogg","ref":[15,1189179,1200627]},{"name":"A_easybass_7.ogg","ref":[15,1200627,1212073]},{"name":"A_shaker 2.ogg","ref":[15,1212073,1223516]},{"name":"C_guitarsolo_14.ogg","ref":[15,1223516,1234957]},{"name":"C_metallead_128.ogg","ref":[15,1234957,1246398]},{"name":"C_metallead_130.ogg","ref":[15,1246398,1257839]},{"name":"A_14basswav_78.ogg","ref":[15,1257839,1269275]},{"name":"introlead_56.ogg","ref":[15,1269275,1280707]},{"name":"A_shaker 1.ogg","ref":[15,1280707,1292135]},{"name":"A_14basswav_15.ogg","ref":[15,1292135,1303562]},{"name":"C_guitarsolo_10.ogg","ref":[15,1303562,1314988]},{"name":"A_14basswav_71.ogg","ref":[15,1314988,1326406]},{"name":"A_elecbass_13.ogg","ref":[15,1326406,1337811]},{"name":"A_14basswav_103.ogg","ref":[15,1337811,1349215]},{"name":"A_14basswav_8.ogg","ref":[15,1349215,1360616]},{"name":"A_14basswav_64.ogg","ref":[15,1360616,1372013]},{"name":"A_14basswav_100.ogg","ref":[15,1372013,1383407]},{"name":"A_14basswav_63.ogg","ref":[15,1383407,1394800]},{"name":"C_metallead_77.ogg","ref":[15,1394800,1406191]},{"name":"A_14basswav_57.ogg","ref":[15,1406191,1417580]},{"name":"A_14basswav_41.ogg","ref":[15,1417580,1428964]},{"name":"A_easybass_21.ogg","ref":[15,1428964,1440344]},{"name":"introlead_37.ogg","ref":[15,1440344,1451721]},{"name":"A_14basswav_56.ogg","ref":[15,1451721,1463092]},{"name":"A_Keys1_15.ogg","ref":[15,1463092,1474462]},{"name":"A_14basswav_53.ogg","ref":[16,0,11369]},{"name":"A_elecbass_23.ogg","ref":[16,11369,22737]},{"name":"introlead_2.ogg","ref":[16,22737,34100]},{"name":"A_14basswav_24.ogg","ref":[16,34100,45460]},{"name":"A_elecbass_48.ogg","ref":[16,45460,56820]},{"name":"A_Keys1_17.ogg","ref":[16,56820,68178]},{"name":"C_guitarsolo_15.ogg","ref":[16,68178,79522]},{"name":"A_14basswav_85.ogg","ref":[16,79522,90865]},{"name":"A_elecbass_25.ogg","ref":[16,90865,102207]},{"name":"A_14basswav_21.ogg","ref":[16,102207,113547]},{"name":"C_hats_11.ogg","ref":[16,113547,124885]},{"name":"A_shaker 3.ogg","ref":[16,124885,136214]},{"name":"introlead_31.ogg","ref":[16,136214,147541]},{"name":"A_14basswav_9.ogg","ref":[16,147541,158861]},{"name":"A_14basswav_5.ogg","ref":[16,158861,170175]},{"name":"A_14basswav_67.ogg","ref":[16,170175,181486]},{"name":"A_14basswav_3.ogg","ref":[16,181486,192791]},{"name":"A_Keys1_18.ogg","ref":[16,192791,204085]},{"name":"A_Keys1_22.ogg","ref":[16,204085,215377]},{"name":"A_14basswav_83.ogg","ref":[16,215377,226667]},{"name":"introlead_38.ogg","ref":[16,226667,237944]},{"name":"A_easybass_26.ogg","ref":[16,237944,249208]},{"name":"A_14basswav_73.ogg","ref":[16,249208,260467]},{"name":"A_easybass_13.ogg","ref":[16,260467,271724]},{"name":"A_14basswav_66.ogg","ref":[16,271724,282974]},{"name":"A_14basswav_87.ogg","ref":[16,282974,294220]},{"name":"A_14basswav_47.ogg","ref":[16,294220,305465]},{"name":"A_Keys1_10.ogg","ref":[16,305465,316702]},{"name":"A_14basswav_1.ogg","ref":[16,316702,327938]},{"name":"A_easybass_12.ogg","ref":[16,327938,339168]},{"name":"introlead_3.ogg","ref":[16,339168,350390]},{"name":"A_14basswav_6.ogg","ref":[16,350390,361610]},{"name":"A_14basswav_93.ogg","ref":[16,361610,372829]},{"name":"B_stupiano_9.ogg","ref":[16,372829,384048]},{"name":"A_Keys1_20.ogg","ref":[16,384048,395264]},{"name":"A_14basswav_52.ogg","ref":[16,395264,406478]},{"name":"A_14basswav_10.ogg","ref":[16,406478,417689]},{"name":"A_14basswav_34.ogg","ref":[16,417689,428894]},{"name":"A_14basswav_11.ogg","ref":[16,428894,440093]},{"name":"A_easybass_28.ogg","ref":[16,440093,451286]},{"name":"introlead_58.ogg","ref":[16,451286,462479]},{"name":"A_easybass_27.ogg","ref":[16,462479,473663]},{"name":"A_easybass_4.ogg","ref":[16,473663,484842]},{"name":"A_wapad_5.ogg","ref":[16,484842,496020]},{"name":"A_easybass_2.ogg","ref":[16,496020,507188]},{"name":"A_14basswav_104.ogg","ref":[16,507188,518339]},{"name":"B_stupiano_1.ogg","ref":[16,518339,529490]},{"name":"A_14basswav_17.ogg","ref":[16,529490,540640]},{"name":"A_14basswav_12.ogg","ref":[16,540640,551777]},{"name":"A_easybass_16.ogg","ref":[16,551777,562912]},{"name":"A_easybass_1.ogg","ref":[16,562912,574041]},{"name":"A_easybass_14.ogg","ref":[16,574041,585161]},{"name":"B_stupiano_4.ogg","ref":[16,585161,596277]},{"name":"A_14basswav_40.ogg","ref":[16,596277,607383]},{"name":"B_stupiano_3.ogg","ref":[16,607383,618478]},{"name":"A_easybass_15.ogg","ref":[16,618478,629572]},{"name":"A_14basswav_62.ogg","ref":[16,629572,640653]},{"name":"A_14basswav_13.ogg","ref":[16,640653,651733]},{"name":"A_easybass_8.ogg","ref":[16,651733,662812]},{"name":"A_14basswav_60.ogg","ref":[16,662812,673882]},{"name":"A_easybass_5.ogg","ref":[16,673882,684949]},{"name":"A_Keys1_8.ogg","ref":[16,684949,696016]},{"name":"A_easybass_10.ogg","ref":[16,696016,707082]},{"name":"A_14basswav_55.ogg","ref":[16,707082,718144]},{"name":"A_easybass_19.ogg","ref":[16,718144,729206]},{"name":"A_easybass_22.ogg","ref":[16,729206,740263]},{"name":"A_14basswav_101.ogg","ref":[16,740263,751311]},{"name":"A_easybass_11.ogg","ref":[16,751311,762355]},{"name":"A_wapad_2.ogg","ref":[16,762355,773391]},{"name":"A_14basswav_80.ogg","ref":[16,773391,784426]},{"name":"A_14basswav_44.ogg","ref":[16,784426,795460]},{"name":"A_14basswav_59.ogg","ref":[16,795460,806472]},{"name":"A_14basswav_39.ogg","ref":[16,806472,817477]},{"name":"A_easybass_25.ogg","ref":[16,817477,828473]},{"name":"A_easybass_24.ogg","ref":[16,828473,839462]},{"name":"A_easybass_23.ogg","ref":[16,839462,850450]},{"name":"A_14basswav_20.ogg","ref":[16,850450,861430]},{"name":"A_easybass_9.ogg","ref":[16,861430,872404]},{"name":"A_easybass_18.ogg","ref":[16,872404,883364]},{"name":"A_wapad_4.ogg","ref":[16,883364,894306]},{"name":"A_14basswav_86.ogg","ref":[16,894306,905236]},{"name":"A_14basswav_7.ogg","ref":[16,905236,916164]},{"name":"A_14basswav_69.ogg","ref":[16,916164,927067]},{"name":"B_stupiano_2.ogg","ref":[16,927067,937960]},{"name":"metro2.ogg","ref":[16,937960,948843]},{"name":"A_14basswav_91.ogg","ref":[16,948843,959708]},{"name":"A_14basswav_19.ogg","ref":[16,959708,970560]},{"name":"B_stupiano_5.ogg","ref":[16,970560,981406]},{"name":"A_14basswav_61.ogg","ref":[16,981406,992222]},{"name":"A_14basswav_22.ogg","ref":[16,992222,1003037]},{"name":"A_14basswav_26.ogg","ref":[16,1003037,1013841]},{"name":"A_wapad_1.ogg","ref":[16,1013841,1024627]},{"name":"A_14basswav_16.ogg","ref":[16,1024627,1035393]},{"name":"A_14basswav_79.ogg","ref":[16,1035393,1046150]},{"name":"A_14basswav_37.ogg","ref":[16,1046150,1056906]},{"name":"A_14basswav_68.ogg","ref":[16,1056906,1067655]},{"name":"A_14basswav_32.ogg","ref":[16,1067655,1078344]},{"name":"metro1.ogg","ref":[16,1078344,1089030]},{"name":"A_14basswav_18.ogg","ref":[16,1089030,1099715]},{"name":"A_easybass_20.ogg","ref":[16,1099715,1110399]},{"name":"introlead_10.ogg","ref":[16,1110399,1121079]},{"name":"A_14basswav_75.ogg","ref":[16,1121079,1131751]},{"name":"A_easybass_6.ogg","ref":[16,1131751,1142411]},{"name":"introlead_35.ogg","ref":[16,1142411,1152893]},{"name":"introlead_33.ogg","ref":[16,1152893,1163353]},{"name":"39.4_lowsnare.ogg","ref":[16,1163353,1173810]},{"name":"A_14basswav_94.ogg","ref":[16,1173810,1184224]},{"name":"A_14basswav_25.ogg","ref":[16,1184224,1194585]},{"name":"A_14basswav_70.ogg","ref":[16,1194585,1204886]},{"name":"A_14basswav_72.ogg","ref":[16,1204886,1214958]},{"name":"C_crash_3_4.ogg","ref":[16,1214958,1224901]},{"name":"A_easybass_17.ogg","ref":[16,1224901,1234718]},{"name":"A_easybass_3.ogg","ref":[16,1234718,1244301]},{"name":"C_kick_1.ogg","ref":[16,1244301,1252244]},{"name":"C_crash_short.ogg","ref":[16,1252244,1260185]},{"name":"C_kick_3_2.ogg","ref":[16,1260185,1268037]},{"name":"C_kick_3.ogg","ref":[16,1268037,1275427]},{"name":"glitchfill_1.ogg","ref":[16,1275427,1281842]},{"name":"glitchfill_4.ogg","ref":[16,1281842,1288150]},{"name":"glitchfill_3.ogg","ref":[16,1288150,1294434]},{"name":"glitchfill_6.ogg","ref":[16,1294434,1300615]},{"name":"glitchfill_2.ogg","ref":[16,1300615,1306791]},{"name":"glitchfill_5_2.ogg","ref":[16,1306791,1312253]}],"refs":[{"path":"oggs.0.6bdbec89.bemuse","hash":"6bdbec8918061d62d3db689ef8b908ef","size":1341175},{"path":"oggs.1.422e9e9f.bemuse","hash":"422e9e9fed35c82fdbe5e936a06bc116","size":1450388},{"path":"oggs.2.62d96a47.bemuse","hash":"62d96a47d04df18da05acb208789288e","size":1447675},{"path":"oggs.3.475b7c18.bemuse","hash":"475b7c18f3e5d4e38781dbe2f29b7cc2","size":1449015},{"path":"oggs.4.5fdb58f6.bemuse","hash":"5fdb58f63e1fdfb58ccf74b684a168d7","size":1449118},{"path":"oggs.5.5791266b.bemuse","hash":"5791266bdd0f48817bca946ef004378e","size":1457792},{"path":"oggs.6.ba3bc0d6.bemuse","hash":"ba3bc0d6d29d3aedf84b23869f241308","size":1465942},{"path":"oggs.7.c5fe14ed.bemuse","hash":"c5fe14ed1f69309024166079a44ec11f","size":1473778},{"path":"oggs.8.a83e02ab.bemuse","hash":"a83e02ab4f16ec21751daee55fbe9941","size":1466775},{"path":"oggs.9.3aca5a14.bemuse","hash":"3aca5a14d5f3b59e939edf9268b0891a","size":1467890},{"path":"oggs.10.5532dd3f.bemuse","hash":"5532dd3f7a6e93c465b20e00c713ee68","size":1462967},{"path":"oggs.11.3d56b4cc.bemuse","hash":"3d56b4ccef68426a7baa36879727ba86","size":1471492},{"path":"oggs.12.8ee1007a.bemuse","hash":"8ee1007a9a6c26ac46ae04b4ceaf62aa","size":1465157},{"path":"oggs.13.aa57294f.bemuse","hash":"aa57294f9f71dbdd3560798dfa4b1eeb","size":1463403},{"path":"oggs.14.b2535f2c.bemuse","hash":"b2535f2c28497044c2795213d41591cd","size":1465685},{"path":"oggs.15.f16aaf76.bemuse","hash":"f16aaf76135d225ad7604f5345221356","size":1474476},{"path":"oggs.16.2635d70a.bemuse","hash":"2635d70ac48b7db9b3fb1a319868f2bf","size":1312267}]}